Workbook

Sheet Resumo
B2: RESUMO DA CARTEIRA
B3: Renda Variável
B4: Capital Investido | C4: ='Carteira RV'!F26 -> 102492.36 | D4: Capital Atual | E4: ='Carteira RV'!G26 -> 125423.57 | G4: Lucro não realizado | H4: ='Carteira RV'!J26 -> 20963.148 | I4: Lucro realizado | K4: =SUM(Vendas!J4:J219) -> -1484.0649
B58: Renda Fixa
B59: Capital Investido | D59: ='Carteira RF'!E9 -> 158019.23 | G59: Capital Atual | J59: ='Carteira RF'!F9 -> 177011.31
B84: Resumo Geral
W261: Renda Variável | X261: =E4 -> 125423.57
W262: Renda Fixa | X262: =J59 -> 177011.31

Sheet Carteira RV
B2: ATIVOS EM CARTEIRA
B3: Código | C3: Nome | D3: Qtde | E3: Preço Médio | F3: Valor Investido | G3: Valor atual | H3: Cotação atual | I3: Rendimento % | J3: Resultado R$ | K3: Tipo de Ativo | L3: Setor
B4: =NFLX!C2 -> NFLX | C4: =NFLX!F2 -> Netflix Inc | D4: =NFLX!J12 -> 8.2276567 | E4: =NFLX!J16*C30 -> 577.82763 | F4: =NFLX!J12*NFLX!J16*C30 -> 4754.1673 | G4: =IF(D4="","",D4*H4) -> 3037.1022 | H4: =IFERROR(__xludf.DUMMYFUNCTION("IF(B5="""","""",GOOGLEFINANCE(B4))*C30"),369.133315) -> 369.13331 | I4: =IF(J4="","",J4/F4) -> -0.36117053 | J4: =IF(G4="","",G4-F4) -> -1717.0651 | K4: =IF(B4="","",VLOOKUP(B4,DB!$A$4:$G$1906,7,0)) -> Stock | L4: =IF(B4="","",VLOOKUP(B4,DB!$A$4:$G$1906,6,0)) -> EUA
B5: =AAPL!C2 -> AAPL | C5: =AAPL!F2 -> Apple Inc | D5: =AAPL!J12 -> 5.7527207 | E5: =AAPL!J16*C30 -> 1167.1215 | F5: =AAPL!J12*AAPL!J16*C30 -> 6714.1238 | G5: =IF(D5="","",D5*H5) -> 10179.47 | H5: =IFERROR(__xludf.DUMMYFUNCTION("IF(B5="""","""",GOOGLEFINANCE(B5))*C30"),1769.5052669999998) -> 1769.5053 | I5: =IF(J5="","",J5/F5) -> 0.51612778 | J5: =IF(G5="","",G5-F5) -> 3465.3458 | K5: Stock | L5: Electronic Components
B6: =META!C2 -> META | C6: =META!F2 -> Meta Platforms Inc | D6: =META!J12 -> 1.2685955 | E6: =META!J16*C30 -> 3747.5832 | F6: =META!J12*META!J16*C30 -> 4754.1673 | G6: =IF(D6="","",D6*H6) -> 4947.1259 | H6: =IFERROR(__xludf.DUMMYFUNCTION("IF(B6="""","""",GOOGLEFINANCE(B6))*C30"),3899.6872459999995) -> 3899.6872 | I6: =IF(J6="","",J6/F6) -> 0.040587249 | J6: =IF(G6="","",G6-F6) -> 192.95857 | K6: =IF(B6="","",VLOOKUP(B6,DB!$A$4:$G$1906,7,0)) -> Stock | L6: =IF(B6="","",VLOOKUP(B6,DB!$A$4:$G$1906,6,0)) -> EUA
B7: =FAST!C2 -> FAST | C7: =FAST!F2 -> Fastenal Co | D7: =FAST!J12 -> 32.423903 | E7: =FAST!J16*C30 -> 203.54498 | F7: =FAST!J12*FAST!J16*C30 -> 6599.7227 | G7: =IF(D7="","",D7*H7) -> 8483.2564 | H7: =IFERROR(__xludf.DUMMYFUNCTION("IF(B7="""","""",GOOGLEFINANCE(B7))*C30"),261.635883) -> 261.63588 | I7: =IF(J7="","",J7/F7) -> 0.28539589 | J7: =IF(G7="","",G7-F7) -> 1883.5337 | K7: =IF(B7="","",VLOOKUP(B7,DB!$A$4:$G$1906,7,0)) -> Stock | L7: =IF(B7="","",VLOOKUP(B7,DB!$A$4:$G$1906,6,0)) -> Industrial Distribution
B8: =APH!C2 -> APH | C8: =APH!F2 -> Amphenol Corp | D8: =APH!J12 -> 27.644698 | E8: =APH!J16*C30 -> 237.08342 | F8: =APH!J12*APH!J16*C30 -> 6554.0995 | G8: =IF(D8="","",D8*H8) -> 12060.478 | H8: =IFERROR(__xludf.DUMMYFUNCTION("IF(B8="""","""",GOOGLEFINANCE(B8))*C30"),436.26732899999996) -> 436.26733 | I8: =IF(J8="","",J8/F8) -> 0.84014271 | J8: =IF(G8="","",G8-F8) -> 5506.3789 | K8: =IF(B8="","",VLOOKUP(B8,DB!$A$4:$G$1906,7,0)) -> Stock | L8: =IF(B8="","",VLOOKUP(B8,DB!$A$4:$G$1906,6,0)) -> Electronic Components
B9: =KO!C2 -> KO | C9: =KO!F2 -> Coca-Cola Co | D9: =KO!J12 -> 19.252848 | E9: =KO!J16*C30 -> 350.72627 | F9: =KO!J12*KO!J16*C30 -> 6752.4797 | G9: =IF(D9="","",D9*H9) -> 8770.9635 | H9: =IFERROR(__xludf.DUMMYFUNCTION("IF(B9="""","""",GOOGLEFINANCE(B9))*C30"),455.56706099999997) -> 455.56706 | I9: =IF(J9="","",J9/F9) -> 0.29892484 | J9: =IF(G9="","",G9-F9) -> 2018.4839 | K9: =IF(B9="","",VLOOKUP(B9,DB!$A$4:$G$1906,7,0)) -> Stock | L9: =IF(B9="","",VLOOKUP(B9,DB!$A$4:$G$1906,6,0)) -> Non-Alcoholic beverages
B10: =VISC11!C2 -> VISC11 | C10: =VISC11!F2 -> Vinci Shopping Centers FI Imobiliario | D10: =VISC11!J12 -> 42 | E10: =VISC11!J16 -> 107.63071 | F10: =VISC11!J12*VISC11!J16 -> 4520.49 | G10: =IF(D10="","",D10*H10) -> 4318.02 | H10: =IFERROR(__xludf.DUMMYFUNCTION("IF(B10="""","""",GOOGLEFINANCE(B10))"),102.81) -> 102.81 | I10: =IF(J10="","",J10/F10) -> -0.044789392 | J10: =IF(G10="","",G10-F10) -> -202.47 | K10: =IF(B10="","",VLOOKUP(B10,DB!$A$4:$G$1906,7,0)) -> Fii | L10: =IF(B10="","",VLOOKUP(B10,DB!$A$4:$G$1906,6,0)) -> BRL Trust DTVM
B11: =KNRI11!C2 -> KNRI11 | C11: =KNRI11!F2 -> Kinea Renda Imobiliaria FII | D11: =KNRI11!J12 -> 30 | E11: =KNRI11!J16 -> 145.71 | F11: =KNRI11!J12*KNRI11!J16 -> 4371.3 | G11: =IF(D11="","",D11*H11) -> 4687.2 | H11: =IFERROR(__xludf.DUMMYFUNCTION("IF(B11="""","""",GOOGLEFINANCE(B11))"),156.24) -> 156.24 | I11: =IF(J11="","",J11/F11) -> 0.072266831 | J11: =IF(G11="","",G11-F11) -> 315.9 | K11: =IF(B11="","",VLOOKUP(B11,DB!$A$4:$G$1906,7,0)) -> Fii | L11: =IF(B11="","",VLOOKUP(B11,DB!$A$4:$G$1906,6,0)) -> INTRAG
B12: =HGRU11!C2 -> HGRU11 | C12: =HGRU11!F2 -> Patria Renda Urbana FII RL Unica | D12: =HGRU11!J12 -> 39 | E12: =HGRU11!J16 -> 124.41051 | F12: =HGRU11!J12*HGRU11!J16 -> 4852.01 | G12: =IF(D12="","",D12*H12) -> 4438.98 | H12: =IFERROR(__xludf.DUMMYFUNCTION("IF(B12="""","""",GOOGLEFINANCE(B12))"),113.82) -> 113.82 | I12: =IF(J12="","",J12/F12) -> -0.085125546 | J12: =IF(G12="","",G12-F12) -> -413.03 | K12: =IF(B12="","",VLOOKUP(B12,DB!$A$4:$G$1906,7,0)) -> Fii | L12: =IF(B12="","",VLOOKUP(B12,DB!$A$4:$G$1906,6,0)) -> CREDIT SUISSE
B13: =HGLG11!C2 -> HGLG11 | C13: =HGLG11!F2 -> Patria Log FII RL | D13: =HGLG11!J12 -> 28 | E13: =HGLG11!J16 -> 157.94214 | F13: =HGLG11!J12*HGLG11!J16 -> 4422.38 | G13: =IF(D13="","",D13*H13) -> 4140.08 | H13: =IFERROR(__xludf.DUMMYFUNCTION("IF(B13="""","""",GOOGLEFINANCE(B13))"),147.86) -> 147.86 | I13: =IF(J13="","",J13/F13) -> -0.063834406 | J13: =IF(G13="","",G13-F13) -> -282.3 | K13: =IF(B13="","",VLOOKUP(B13,DB!$A$4:$G$1906,7,0)) -> Fii | L13: =IF(B13="","",VLOOKUP(B13,DB!$A$4:$G$1906,6,0)) -> CREDIT SUISSE
B14: =B3SA3!C2 -> B3SA3 | C14: =B3SA3!F2 -> B3 SA Brasil Bolsa Balcao | D14: =B3SA3!J12 -> 386 | E14: =B3SA3!J16 -> 12.484326 | F14: =B3SA3!J12*B3SA3!J16 -> 4818.95 | G14: =IF(D14="","",D14*H14) -> 6932.56 | H14: =IFERROR(__xludf.DUMMYFUNCTION("IF(B14="""","""",GOOGLEFINANCE(B14))"),17.96) -> 17.96 | I14: =IF(J14="","",J14/F14) -> 0.43860385 | J14: =IF(G14="","",G14-F14) -> 2113.61 | K14: =IF(B14="","",VLOOKUP(B14,DB!$A$4:$G$1906,7,0)) -> Ação | L14: =IF(B14="","",VLOOKUP(B14,DB!$A$4:$G$1906,6,0)) -> Serviços Financeiros Diversos
B15: =WEGE3!C2 -> WEGE3 | C15: =WEGE3!F2 -> Weg Cedear | D15: =WEGE3!J12 -> 126 | E15: =WEGE3!J16 -> 42.027381 | F15: =WEGE3!J12*WEGE3!J16 -> 5295.45 | G15: =IF(D15="","",D15*H15) -> 6434.82 | H15: =IFERROR(__xludf.DUMMYFUNCTION("IF(B15="""","""",GOOGLEFINANCE(""BVMF:""&B15))"),51.07) -> 51.07 | I15: =IF(J15="","",J15/F15) -> 0.21516018 | J15: =IF(G15="","",G15-F15) -> 1139.37 | K15: =IF(B15="","",VLOOKUP(B15,DB!$A$4:$G$1906,7,0)) -> Ação | L15: =IF(B15="","",VLOOKUP(B15,DB!$A$4:$G$1906,6,0)) -> Motores, Compressores e Outros
B16: =TAEE3!C2 -> TAEE3 | C16: =TAEE3!F2 -> Transmissora Alianca de Enrga Eltrca S/A | D16: =TAEE3!J12 -> 406 | E16: =TAEE3!J16 -> 12.204655 | F16: =TAEE3!J12*TAEE3!J16 -> 4955.09 | G16: =IF(D16="","",D16*H16) -> 5440.4 | H16: =IFERROR(__xludf.DUMMYFUNCTION("IF(B16="""","""",GOOGLEFINANCE(B16))"),13.4) -> 13.4 | I16: =IF(J16="","",J16/F16) -> 0.097941712 | J16: =IF(G16="","",G16-F16) -> 485.31 | K16: =IF(B16="","",VLOOKUP(B16,DB!$A$4:$G$1906,7,0)) -> Ação | L16: =IF(B16="","",VLOOKUP(B16,DB!$A$4:$G$1906,6,0)) -> Energia Elétrica
B17: =PSSA3!C2 -> PSSA3 | C17: =PSSA3!F2 -> Porto Seguro SA | D17: =PSSA3!J12 -> 120 | E17: =PSSA3!J16 -> 33.16125 | F17: =PSSA3!J12*PSSA3!J16 -> 3979.35 | G17: =IF(D17="","",D17*H17) -> 5650.8 | H17: =IFERROR(__xludf.DUMMYFUNCTION("IF(B17="""","""",GOOGLEFINANCE(B17))"),47.09) -> 47.09 | I17: =IF(J17="","",J17/F17) -> 0.42003091 | J17: =IF(G17="","",G17-F17) -> 1671.45 | K17: =IF(B17="","",VLOOKUP(B17,DB!$A$4:$G$1906,7,0)) -> Ação | L17: =IF(B17="","",VLOOKUP(B17,DB!$A$4:$G$1906,6,0)) -> Seguradoras
B18: =ITUB3!C2 -> ITUB3 | C18: =ITUB3!F2 -> Itau Unibanco Holding Cedear | D18: =ITUB3!J12 -> 142 | E18: =ITUB3!J16 -> 29.209718 | F18: =ITUB3!J12*ITUB3!J16 -> 4147.78 | G18: =IF(D18="","",D18*H18) -> 6544.78 | H18: =IFERROR(__xludf.DUMMYFUNCTION("IF(B18="""","""",GOOGLEFINANCE(""BVMF:""&B18))"),46.09) -> 46.09 | I18: =IF(J18="","",J18/F18) -> 0.5778995 | J18: =IF(G18="","",G18-F18) -> 2397 | K18: =IF(B18="","",VLOOKUP(B18,DB!$A$4:$G$1906,7,0)) -> Ação | L18: =IF(B18="","",VLOOKUP(B18,DB!$A$4:$G$1906,6,0)) -> Bancos
B19: =HYPE3!C2 -> HYPE3 | C19: =HYPE3!F2 -> Hypera SA | D19: =HYPE3!J12 -> 211 | E19: =HYPE3!J16 -> 25.613554 | F19: =HYPE3!J12*HYPE3!J16 -> 5404.46 | G19: =IF(D19="","",D19*H19) -> 5175.83 | H19: =IFERROR(__xludf.DUMMYFUNCTION("IF(B19="""","""",GOOGLEFINANCE(B19))"),24.53) -> 24.53 | I19: =IF(J19="","",J19/F19) -> -0.042303949 | J19: =IF(G19="","",G19-F19) -> -228.63 | K19: =IF(B19="","",VLOOKUP(B19,DB!$A$4:$G$1906,7,0)) -> Ação | L19: =IF(B19="","",VLOOKUP(B19,DB!$A$4:$G$1906,6,0)) -> Medicamentos e Outros Produtos
B20: =EGIE3!C2 -> EGIE3 | C20: =EGIE3!F2 -> Engie Brasil Energia SA | D20: =EGIE3!J12 -> 161 | E20: =EGIE3!J16 -> 29.905081 | F20: =EGIE3!J12*EGIE3!J16 -> 4814.718 | G20: =IF(D20="","",D20*H20) -> 4685.1 | H20: =IFERROR(__xludf.DUMMYFUNCTION("IF(B20="""","""",GOOGLEFINANCE(B20))"),29.1) -> 29.1 | I20: =IF(J20="","",J20/F20) -> -0.026921203 | J20: =IF(G20="","",G20-F20) -> -129.618 | K20: =IF(B20="","",VLOOKUP(B20,DB!$A$4:$G$1906,7,0)) -> Ação | L20: =IF(B20="","",VLOOKUP(B20,DB!$A$4:$G$1906,6,0)) -> Energia Elétrica
B21: =BBDC3!C2 -> BBDC3 | C21: =BBDC3!F2 -> Banco Bradesco Cedear | D21: =BBDC3!J12 -> 376 | E21: =BBDC3!J16 -> 13.606782 | F21: =BBDC3!J12*BBDC3!J16 -> 5116.15 | G21: =IF(D21="","",D21*H21) -> 5929.52 | H21: =IFERROR(__xludf.DUMMYFUNCTION("IF(B21="""","""",GOOGLEFINANCE(""BVMF:""&B21))"),15.77) -> 15.77 | I21: =IF(J21="","",J21/F21) -> 0.15898087 | J21: =IF(G21="","",G21-F21) -> 813.37 | K21: =IF(B21="","",VLOOKUP(B21,DB!$A$4:$G$1906,7,0)) -> Ação | L21: =IF(B21="","",VLOOKUP(B21,DB!$A$4:$G$1906,6,0)) -> Bancos
B22: =ABEV3!C2 -> ABEV3 | C22: =ABEV3!F2 -> Amebv Cedear | D22: =ABEV3!J12 -> 378 | E22: =ABEV3!J16 -> 13.286032 | F22: =ABEV3!J12*ABEV3!J16 -> 5022.12 | G22: =IF(D22="","",D22*H22) -> 5790.96 | H22: =IFERROR(__xludf.DUMMYFUNCTION("IF(B22="""","""",GOOGLEFINANCE(""BVMF:""&B22))"),15.32) -> 15.32 | I22: =IF(J22="","",J22/F22) -> 0.15309073 | J22: =IF(G22="","",G22-F22) -> 768.84 | K22: =IF(B22="","",VLOOKUP(B22,DB!$A$4:$G$1906,7,0)) -> Ação | L22: =IF(B22="","",VLOOKUP(B22,DB!$A$4:$G$1906,6,0)) -> Cervejas e Refrigerantes
B23: =BTC!C2 -> BTCUSD | C23: =BTC!F2 -> Bitcoin | D23: =BTC!J12 -> 0.00763929 | E23: =BTC!J16 -> 159254.36 | F23: =BTC!J13 -> 2667.144 | G23: =IF(D23="","",D23*H23) -> 3355.4548 | H23: =IFERROR(__xludf.DUMMYFUNCTION("IF(B23="""","""",(GOOGLEFINANCE(B23)*C30))"),439236.47862999997) -> 439236.48 | I23: =IF(J23="","",J23/F23) -> 0.25807037 | J23: =IF(G23="","",G23-F23) -> 688.31083 | K23: =IF(B23="","",VLOOKUP(B23,DB!$A$4:$G$1906,7,0)) -> Criptomoeda | L23: =IF(B23="","",VLOOKUP(B23,DB!$A$4:$G$1906,6,0)) -> Criptos
B24: =ETH!C2 -> ETHUSD | C24: =ETH!F2 -> Ethereum | D24: =ETH!J12 -> 0.17436968 | E24: =ETH!J16 -> 6284.174 | F24: =ETH!J13 -> 1976.2118 | G24: =IF(D24="","",D24*H24) -> 2452.6115 | H24: =IFERROR(__xludf.DUMMYFUNCTION("IF(B24="""","""",(GOOGLEFINANCE(B24)*C30))"),14065.58449964) -> 14065.585 | I24: =IF(J24="","",J24/F24) -> 0.24106713 | J24: =IF(G24="","",G24-F24) -> 476.39969 | K24: =IF(B24="","",VLOOKUP(B24,DB!$A$4:$G$1906,7,0)) -> Criptomoeda | L24: =IF(B24="","",VLOOKUP(B24,DB!$A$4:$G$1906,6,0)) -> Criptos
B25: =PAXGOLD!C2 -> Pax Gold | C25: Pax Gold | D25: =PAXGOLD!J12 -> 0.07249708 | E25: =PAXGOLD!J16 -> 26388.536 | F25: =PAXGOLD!J13 -> 1912.5989 | G25: =IF(D25="","",D25*H25) -> 1968.0594 | H25: 27146.74 | I25: =IF(J25="","",J25/F25) -> 0.028997437 | J25: =IF(G25="","",G25-F25) -> 55.460467 | K25: Criptomoeda | L25: Criptos
B26: Total | F26: =SUM(F4:F24) -> 102492.36 | G26: =SUM(G4:G25) -> 125423.57 | H26: - | I26: =AVERAGE(I4:I22) -> 0.18373726 | J26: =SUM(J4:J24) -> 20963.148 | K26: - | L26: -
B30: Valor Dólar | C30: =IFERROR(__xludf.DUMMYFUNCTION("GOOGLEFINANCE(""CURRENCY:USDBRL"")"),5.1880999999999995) -> 5.1881

Sheet Carteira RF
B2: APLICAÇÕES EM CARTEIRA
B3: Código | C3: Nome | D3: Tipo de aplicação | E3: Valor Bruto Investido | F3: Valor Líquido atual | G3: Valorizacão R$ | H3: Valorização %
B4: ='Tesouro Selic 2027'!C2 -> TS2027 | C4: ='Tesouro Selic 2027'!E2 -> Tesouro Selic 2027 | D4: Tesouro Direto | E4: ='Tesouro Selic 2027'!J3 -> 29884.98 | F4: ='Tesouro Selic 2027'!J4 -> 38297.07 | G4: ='Tesouro Selic 2027'!J5 -> 8412.09 | H4: ='Tesouro Selic 2027'!J6 -> 0.2814822
B5: ='Tesouro Renda+ 2055'!C2 -> TR+2055 | C5: ='Tesouro Renda+ 2055'!E2 -> Tesouro Renda+ 2055 | D5: Tesouro Direto | E5: ='Tesouro Renda+ 2055'!J3 -> 6449.86 | F5: ='Tesouro Renda+ 2055'!J4 -> 6154.86 | G5: ='Tesouro Renda+ 2055'!J5 -> -295 | H5: ='Tesouro Renda+ 2055'!J6 -> -0.045737427
B6: ='Tesouro Educa+ 2043'!C2 -> TE+2043 | C6: ='Tesouro Educa+ 2043'!E2 -> Tesouro Educa+ 2043 | D6: Tesouro Direto | E6: ='Tesouro Educa+ 2043'!J3 -> 3794.23 | F6: ='Tesouro Educa+ 2043'!J4 -> 3786.53 | G6: ='Tesouro Educa+ 2043'!J5 -> -7.7 | H6: ='Tesouro Educa+ 2043'!J6 -> -0.0020293973
B7: ='Tesouro Selic 2028'!C2 -> TS2028 | C7: ='Tesouro Selic 2028'!E2 -> Tesouro Selic 2028 | D7: Tesouro Direto | E7: ='Tesouro Selic 2028'!J3 -> 67343.78 | F7: ='Tesouro Selic 2028'!J4 -> 75978.29 | G7: ='Tesouro Selic 2028'!J5 -> 8634.51 | H7: ='Tesouro Selic 2028'!J6 -> 0.1282154
B8: ='Tesouro Selic 2031'!C2 -> TS2031 | C8: ='Tesouro Selic 2031'!E2 -> Tesouro Selic 2031 | D8: =IF(B8="","",VLOOKUP(B8,DB!$A$4:$G$1906,7,0)) -> Tesouro Direto | E8: ='Tesouro Selic 2031'!J3 -> 50546.38 | F8: ='Tesouro Selic 2031'!J4 -> 52794.56 | G8: ='Tesouro Selic 2031'!J5 -> 2248.18 | H8: ='Tesouro Selic 2031'!J6 -> 0.044477567
B9: Total | E9: =SUM(E4:E8) -> 158019.23 | F9: =SUM(F4:F8) -> 177011.31 | G9: =SUM(G4:G8) -> 18992.08 | H9: =SUM(H4:H8)/COUNT(H4:H8) -> 0.08128167

Sheet AtivoChove
B2: ID | C2: ITUB3 | D2: Nome do Ativo | F2: =IFERROR(__xludf.DUMMYFUNCTION("IF(C2="""","""",GOOGLEFINANCE(C2,""Name""))"),"Itau Unibanco Holding Cedear") -> Itau Unibanco Holding Cedear
B3: Data | C3: Operação | D3: Qtde | E3: Valor unitário | F3: Taxas/Impostos | G3: Valor da operação | H3: Gráfico | K3: Dias graf
G4: =E4*D4 -> 0 | H4: =IFERROR(__xludf.DUMMYFUNCTION("IF(C2="""","""",SPARKLINE(GOOGLEFINANCE(C2,""price"",TODAY()-K4,TODAY())))"),"") | K4: 30
I10: Qtde Comprada | J10: =SUMIFS(D4:D21,C4:C21,"COMPRA") -> 0
I11: Qtde Vendida | J11: =SUMIFS(D4:D21,C4:C21,"VENDA") -> 0
I12: Qtde em Carteira | J12: =J10-J11 -> 0
I13: Valor das Compras | J13: =SUMIFS(G4:G21,C4:C21,"COMPRA") -> 0
I14: Valor das Vendas | J14: =SUMIFS(E4:E21,C4:C21,"VENDA") -> 0
I15: Total de Taxas | J15: =SUM(F4:F21) -> 0
I16: Preço Médio | J16: =IF(J10<>0,((J13+J15)/J10),"")

Sheet Vendas
B2: VENDA DE ATIVOS
B3: Tipo de negociação | C3: Código | D3: Preço médio de compra | E3: Preço de venda | F3: Qtde | G3: Valor bruto da Compra | H3: Valor bruto da Venda | I3: Taxa | J3: Lucro líquido | K3: Mês/ano da venda
B4: Venda | C4: LTC | D4: 511.75458 | E4: 313.87 | F4: 2.44145 | G4: =F4*D4 -> 1249.4232 | H4: =F4*E4 -> 766.29791 | I4: 5.27 | J4: =(E4-D4)*F4-I4 -> -488.3953 | K4: 44718
B5: Venda | C5: ETH | D5: 12975.982 | E5: 9125.77 | F5: 0.14231757 | G5: =F5*D5 -> 1846.7102 | H5: =F5*E5 -> 1298.7574 | I5: 8.98 | J5: =(E5-D5)*F5-I5 -> -556.93279 | K5: 44718
B6: Venda | C6: BTC | D6: 196789.07 | E6: 150000 | F6: 0.00916938 | G6: =F6*D6 -> 1804.4338 | H6: =F6*E6 -> 1375.407 | I6: 9.71 | J6: =(E6-D6)*F6-I6 -> -438.73677 | K6: 44718

Sheet Evolução Patrimônio
B2: Evolução de patrimônio
B3: Mês | C3: Total Investido no mês | D3: Total retirado no período | E3: Alocação líquida | F3: Patrimônio total | G3: Evolução patrimonial | H3: %
B4: 44621 | C4: 5607.59 | D4: 0 | E4: =C4-D4 -> 5607.59 | F4: =62107.17+E4 -> 67714.76 | G4: =F4-62107.17 -> 5607.59 | H4: =G4/F4 -> 0.082811931
B5: 44652 | C5: 4000 | D5: =12769+946 -> 13715 | E5: =C5-D5 -> -9715 | F5: =F4+E5 -> 57999.76 | G5: =F5-F4 -> -9715 | H5: =G5/F4 -> -0.14346946
B6: 44682 | C6: 0 | D6: 9812 | E6: =C6-D6 -> -9812 | F6: =F5+E6 -> 48187.76 | G6: =F6-F5 -> -9812 | H6: =G6/F5 -> -0.16917311
B7: 44713 | C7: 0 | D7: =1484.06+4515.55 -> 5999.61 | E7: =C7-D7 -> -5999.61 | F7: =F6+E7 -> 42188.15 | G7: =F7-F6 -> -5999.61 | H7: =G7/F6 -> -0.12450485
B8: 44743 | C8: 8935.5 | D8: 1500 | E8: =C8-D8 -> 7435.5 | F8: 49518.77 | G8: =F8-F7 -> 7330.62 | H8: =G8/F7 -> 0.17376017
B9: 44774 | C9: 0 | D9: 500 | E9: =C9-D9 -> -500 | F9: =42137.81+6729.22 -> 48867.03 | G9: =F9-F8 -> -651.74 | H9: =G9/F8 -> -0.013161474
B10: 44805 | C10: 7050 | D10: 846 | E10: =C10-D10 -> 6204 | F10: 56110.88 | G10: =F10-F9 -> 7243.85 | H10: =G10/F9 -> 0.14823594
B11: 44927 | C11: 6301 | D11: 0 | E11: =C11-D11 -> 6301 | F11: =10387.24+51310.66 -> 61697.9 | G11: =F11-F10 -> 5587.02 | H11: =G11/F10 -> 0.099571064
B12: 44958 | C12: 0 | D12: =1332.87+899.47 -> 2232.34 | E12: =C12-D12 -> -2232.34 | F12: =61697.9+E12 -> 59465.56 | G12: =F12-F11 -> -2232.34 | H12: =G12/F11 -> -0.036181783
B13: 44986 | C13: 4000 | D13: 0 | E13: =C13-D13 -> 4000 | F13: =F12+E13 -> 63465.56 | G13: =F13-F12 -> 4000 | H13: =G13/F12 -> 0.067265826
B14: 45047 | C14: 0 | D14: 0 | E14: =C14-D14 -> 0 | F14: =67000 -> 67000 | G14: =F14-F13 -> 3534.44 | H14: =G14/F13 -> 0.055690677
B15: 45139 | C15: 0 | D15: =5620+22243.59 -> 27863.59 | E15: =C15-D15 -> -27863.59 | F15: =14986.38+40857.9 -> 55844.28 | G15: =F15-F14 -> -11155.72 | H15: =G15/F14 -> -0.16650328
B16: 45231 | C16: =1174.98+6973.65+259.59 -> 8408.22 | D16: 0 | E16: =C16-D16 -> 8408.22 | F16: =19049.055349075+43723.33 -> 62772.385 | G16: =F16-F15 -> 6928.1053 | H16: =G16/F15 -> 0.12406115
B17: 45292 | C17: 6640 | D17: 1149.47 | E17: =C17-D17 -> 5490.53 | F17: 71457.31 | G17: =F17-F16 -> 8684.9247 | H17: =G17/F16 -> 0.13835582
B18: 45323 | C18: =2982.99+12015.08 -> 14998.07 | D18: 0 | E18: =C18-D18 -> 14998.07 | F18: 85081.826 | G18: =F18-F17 -> 13624.516 | H18: =G18/F17 -> 0.19066651
B19: 45352 | C19: 4998.95 | D19: 35453.76 | E19: =C19-D19 -> -30454.81 | F19: =25417.74+30509.27 -> 55927.01 | G19: =F19-F18 -> -29154.816 | H19: =G19/F18 -> -0.34266796
B20: 45413 | C20: =1997.64+1151.13 -> 3148.77 | D20: 0 | E20: =C20-D20 -> 3148.77 | F20: =23804.89+33033.15 -> 56838.04 | G20: =F20-F19 -> 911.03 | H20: =G20/F19 -> 0.016289625
B21: 45505 | C21: =1632.8+2118.54+1032.11 -> 4783.45 | D21: 0 | E21: =C21-D21 -> 4783.45 | F21: =32558.39+42197.3 -> 74755.69 | G21: =F21-F20 -> 17917.65 | H21: =G21/F20 -> 0.31524046
B22: 45536 | C22: 6086.91 | D22: 0 | E22: =C22-D22 -> 6086.91 | F22: =35512.47+48582.99 -> 84095.46 | G22: =F22-F21 -> 9339.77 | H22: =G22/F21 -> 0.12493725
B23: 45566 | C23: 31893.23 | D23: =2018.79+4195.74 -> 6214.53 | E23: =C23-D23 -> 25678.7 | F23: =46543.65+62145.89 -> 108689.54 | G23: =F23-F22 -> 24594.08 | H23: =G23/F22 -> 0.29245431
B24: 45597 | C24: 8957.03 | D24: 0 | E24: =C24-D24 -> 8957.03 | F24: =50581.3+66589.87 -> 117171.17 | G24: =F24-F23 -> 8481.63 | H24: =G24/F23 -> 0.078035384
B25: 45658 | C25: 12427.15 | D25: 0 | E25: =C25-D25 -> 12427.15 | F25: =54177.43+72735.81 -> 126913.24 | G25: =F25-F24 -> 9742.07 | H25: =G25/F24 -> 0.083143917
B26: 45748 | C26: 8913.13 | D26: 0 | E26: =C26-D26 -> 8913.13 | F26: =58288.94+77084.23 -> 135373.17 | G26: =F26-F25 -> 8459.93 | H26: =G26/F25 -> 0.06665916
B27: 45839 | C27: 16130.44 | D27: 0 | E27: =C27-D27 -> 16130.44 | F27: =69608.91+95124.65 -> 164733.56 | G27: =F27-F26 -> 29360.39 | H27: =G27/F26 -> 0.21688485
B28: 45901 | C28: =2887.65+'Tesouro Selic 2028'!D6+(642*'Carteira RV'!C30) -> 16652.32 | D28: 0 | E28: =C28-D28 -> 16652.32 | F28: =71079.93+96975.42+E28 -> 184707.67 | G28: =F28-F27 -> 19974.11 | H28: =G28/F27 -> 0.12125101
B29: 45931 | C29: =(366*'Carteira RV'!C30)+3009.21+'Tesouro Selic 2028'!D7 -> 10863.305 | D29: 0 | E29: =C29-D29 -> 10863.305 | F29: =81107.39+119550.43 -> 200657.82 | G29: =F29-F28 -> 15950.15 | H29: =G29/F28 -> 0.086353478
B30: 46023 | C30: =3126.31+3006.12+16999.7+2499 -> 25631.13 | D30: 0 | E30: =C30-D30 -> 25631.13 | F30: =105040.19+139032.29 -> 244072.48 | G30: =F30-F29 -> 43414.66 | H30: =G30/F29 -> 0.21636166
B31: 46082 | C31: 29618.604 | D31: 0 | E31: =C31-D31 -> 29618.604 | F31: =111213.65+175393.41 -> 286607.06 | G31: =F31-F30 -> 42534.58 | H31: =G31/F30 -> 0.17427028
B32: 46204 | C32: =((AAPL!G16+AAPL!G15+FAST!G18+KO!G17+APH!G16+APH!G17)*'Carteira RV'!C30)+(EGIE3!G25+KNRI11!G24+HGRU11!G25+HGLG11!G25+ITUB3!G23+WEGE3!G26+TAEE3!G26+PSSA3!G21+HYPE3!G27+B3SA3!G27+BBDC3!G27+ABEV3!G26+'Tesouro Selic 2031'!D7+'Tesouro Educa+ 2043'!D4+'Tesouro Renda+ 2055'!D4) -> 36981.927 | D32: =SUM('Tesouro Selic 2031'!D6+'Tesouro IPCA+ 2035'!D21) -> -38526.94 | E32: =C32+D32 -> -1545.013 | F32: =120984.13+167991.3 -> 288975.43 | G32: =F32-F31 -> 2368.37 | H32: =G32/F31 -> 0.008263474
B33: 46266 | C33: =3168.1+637.07+2149.32 -> 5954.49 | D33: 0 | E33: =C33+D33 -> 5954.49 | F33: =124151.31+158019.23 -> 282170.54 | G33: =F33-F32 -> -6804.89 | H33: =G33/F32 -> -0.023548334

Sheet AAPL
B2: ID | C2: AAPL | D2: Nome do Ativo | F2: =IFERROR(__xludf.DUMMYFUNCTION("IF(C2="""","""",GOOGLEFINANCE(C2,""Name""))"),"Apple Inc") -> Apple Inc
B3: Data | C3: Operação | D3: Qtde | E3: Valor unitário | F3: Taxas/Impostos | G3: Valor da operação | H3: Gráfico | K3: Dias graf
B4: 44655 | C4: COMPRA | D4: 1 | E4: 117.19 | F4: 0 | G4: =E4*D4 -> 117.19 | H4: =IFERROR(__xludf.DUMMYFUNCTION("IF(C2="""","""",SPARKLINE(GOOGLEFINANCE(C2,""price"",TODAY()-K4,TODAY())))"),"") | K4: 30
B5: 45551 | C5: COMPRA | D5: 0.16 | E5: 216.36 | F5: 0 | G5: =E5*D5 -> 34.6176
B6: 45595 | C6: COMPRA | D6: 0.4894 | E6: 230.88 | F6: 0 | G6: =E6*D6 -> 112.99267
B7: 45628 | C7: COMPRA | D7: 0.2251 | E7: 239.8 | F7: 0 | G7: =E7*D7 -> 53.97898
B8: 45667 | C8: COMPRA | D8: =G8/E8 -> 0.31035339 | E8: 241.66 | F8: 0 | G8: 75
B9: 45758 | C9: COMPRA | D9: =G9/E9 -> 0.25822785 | E9: 197.5 | F9: 0 | G9: 51
B10: 45848 | C10: COMPRA | D10: 1.1184211 | E10: 212.8 | F10: 0 | G10: =E10*D10 -> 238 | I10: Qtde Comprada | J10: =SUMIFS(D4:D21,C4:C21,"COMPRA") -> 5.7527207
B11: 45939 | C11: COMPRA | D11: 0.23921569 | E11: 255 | F11: 0 | G11: =E11*D11 -> 61.000001 | I11: Qtde Vendida | J11: =SUMIFS(D4:D21,C4:C21,"VENDA") -> 0
B12: 46000 | C12: COMPRA | D12: 0.32314818 | E12: 278.51 | F12: 0 | G12: =E12*D12 -> 90 | I12: Qtde em Carteira | J12: =J10-J11 -> 5.7527207
B13: 46051 | C13: COMPRA | D13: 0.37454234 | E13: 256.74 | F13: 0 | G13: =E13*D13 -> 96.16 | I13: Valor das Compras | J13: =SUMIFS(G4:G21,C4:C21,"COMPRA") -> 1294.1393
B14: 46087 | C14: COMPRA | D14: 0.42160224 | E14: 256.64 | F14: 0 | G14: =E14*D14 -> 108.2 | I14: Valor das Vendas | J14: =SUMIFS(E4:E21,C4:C21,"VENDA") -> 0
B15: 46205 | C15: COMPRA | D15: 0.41619249 | E15: 307.55 | F15: 0 | G15: =E15*D15 -> 128 | I15: Total de Taxas | J15: =SUM(F4:F21) -> 0
B16: 46205 | C16: COMPRA | D16: 0.41651752 | E16: 307.31 | F16: 0 | G16: =E16*D16 -> 128 | I16: Preço Médio | J16: =IF(J10<>0,((J13+J15)/J10),"") -> 224.96125
G17: =E17*D17 -> 0
G18: =E18*D18 -> 0
G19: =E19*D19 -> 0
G20: =E20*D20 -> 0
G21: =E21*D21 -> 0

Sheet NFLX
B2: ID | C2: NFLX | D2: Nome do Ativo | F2: =IFERROR(__xludf.DUMMYFUNCTION("IF(C2="""","""",GOOGLEFINANCE(C2,""Name""))"),"Netflix Inc") -> Netflix Inc
B3: Data | C3: Operação | D3: Qtde | E3: Valor unitário | F3: Taxas/Impostos | G3: Valor da operação | H3: Gráfico | K3: Dias graf
B4: 45848 | C4: COMPRA | D4: 1.9168564 | E4: 125.205 | F4: 0 | G4: 240 | H4: =IFERROR(__xludf.DUMMYFUNCTION("IF(C2="""","""",SPARKLINE(GOOGLEFINANCE(C2,""price"",TODAY()-K4,TODAY())))"),"") | K4: 50
B5: 45922 | C5: COMPRA | D5: 2.6184844 | E5: 122.59 | F5: 0 | G5: 321
B6: 45939 | C6: COMPRA | D6: 0.4965001 | E6: 122.86 | F6: 0 | G6: 61
B7: 46000 | C7: COMPRA | D7: 0.9375 | E7: 96 | F7: 0 | G7: =E7*D7 -> 90
B8: 46051 | C8: COMPRA | D8: 1.1593923 | E8: 82.94 | F8: 0 | G8: =E8*D8 -> 96.16
B9: 46087 | C9: COMPRA | D9: 1.0989234 | E9: 98.46 | F9: 0 | G9: =E9*D9 -> 108.2
G10: =E10*D10 -> 0 | I10: Qtde Comprada | J10: =SUMIFS(D3:D20,C3:C20,"COMPRA") -> 8.2276567
G11: =E11*D11 -> 0 | I11: Qtde Vendida | J11: =SUMIFS(D4:D21,C4:C21,"VENDA") -> 0
G12: =E12*D12 -> 0 | I12: Qtde em Carteira | J12: =J10-J11 -> 8.2276567
G13: =E13*D13 -> 0 | I13: Valor das Compras | J13: =SUMIFS(G4:G21,C4:C21,"COMPRA") -> 916.36
G14: =E14*D14 -> 0 | I14: Valor das Vendas | J14: =SUMIFS(E4:E21,C4:C21,"VENDA") -> 0
G15: =E15*D15 -> 0 | I15: Total de Taxas | J15: =SUM(F4:F21) -> 0
G16: =E16*D16 -> 0 | I16: Preço Médio | J16: =IF(J10<>0,((J13+J15)/J10),"") -> 111.37558
G17: =E17*D17 -> 0
G18: =E18*D18 -> 0
G19: =E19*D19 -> 0
G20: =E20*D20 -> 0
G21: =E21*D21 -> 0

Sheet META
B2: ID | C2: META | D2: Nome do Ativo | F2: =IFERROR(__xludf.DUMMYFUNCTION("IF(C2="""","""",GOOGLEFINANCE(C2,""Name""))"),"Meta Platforms Inc") -> Meta Platforms Inc
B3: Data | C3: Operação | D3: Qtde | E3: Valor unitário | F3: Taxas/Impostos | G3: Valor da operação | H3: Gráfico | K3: Dias graf
B4: 45848 | C4: COMPRA | D4: 0.33116238 | E4: 724.72 | F4: 0 | G4: =E4*D4 -> 240 | H4: =IFERROR(__xludf.DUMMYFUNCTION("IF(C2="""","""",SPARKLINE(GOOGLEFINANCE(C2,""price"",TODAY()-K4,TODAY())))"),"") | K4: 60
B5: 45922 | C5: COMPRA | D5: 0.41643423 | E5: 770.83 | F5: 0 | G5: =E5*D5 -> 321
B6: 45939 | C6: COMPRA | D6: 0.08473399 | E6: 719.9 | F6: 0 | G6: =E6*D6 -> 60.999999
B7: 46000 | C7: COMPRA | D7: 0.13712405 | E7: 656.34 | F7: 0 | G7: =E7*D7 -> 89.999999
B8: 46051 | C8: COMPRA | D8: 0.13156563 | E8: 730.89 | F8: 0 | G8: =E8*D8 -> 96.160003
B9: 46087 | C9: COMPRA | D9: 0.16757527 | E9: 645.68 | F9: 0 | G9: =E9*D9 -> 108.2
G10: =E10*D10 -> 0 | I10: Qtde Comprada | J10: =SUMIFS(D3:D20,C3:C20,"COMPRA") -> 1.2685955
G11: =E11*D11 -> 0 | I11: Qtde Vendida | J11: =SUMIFS(D4:D21,C4:C21,"VENDA") -> 0
G12: =E12*D12 -> 0 | I12: Qtde em Carteira | J12: =J10-J11 -> 1.2685955
G13: =E13*D13 -> 0 | I13: Valor das Compras | J13: =SUMIFS(G4:G21,C4:C21,"COMPRA") -> 916.36
G14: =E14*D14 -> 0 | I14: Valor das Vendas | J14: =SUMIFS(E4:E21,C4:C21,"VENDA") -> 0
G15: =E15*D15 -> 0 | I15: Total de Taxas | J15: =SUM(F4:F21) -> 0
G16: =E16*D16 -> 0 | I16: Preço Médio | J16: =IF(J10<>0,((J13+J15)/J10),"") -> 722.34212
G17: =E17*D17 -> 0
G18: =E18*D18 -> 0
G19: =E19*D19 -> 0
G20: =E20*D20 -> 0
G21: =E21*D21 -> 0

Sheet FAST
B2: ID | C2: FAST | D2: Nome do Ativo | F2: =IFERROR(__xludf.DUMMYFUNCTION("IF(C2="""","""",GOOGLEFINANCE(C2,""Name""))"),"Fastenal Co") -> Fastenal Co
B3: Data | C3: Operação | D3: Qtde | E3: Valor unitário | F3: Taxas/Impostos | G3: Valor da operação | H3: Gráfico | K3: Dias graf
B4: 44630 | C4: COMPRA | D4: 2 | E4: 27.15 | F4: 0 | G4: =E4*D4 -> 54.3 | H4: =IFERROR(__xludf.DUMMYFUNCTION("IF(C2="""","""",SPARKLINE(GOOGLEFINANCE(C2,""price"",TODAY()-K4,TODAY())))"),"") | K4: 30
B5: 44841 | C5: COMPRA | D5: 2 | E5: 23.15 | F5: 0 | G5: =E5*D5 -> 46.3
B6: 45246 | C6: COMPRA | D6: 2 | E6: 30.285 | F6: 0.3 | G6: =(E6*D6)+F6 -> 60.87
B7: 45505 | C7: COMPRA | D7: 1.8 | E7: 33.835 | F7: 0 | G7: =(E7*D7)+F7 -> 60.903
B8: 45551 | C8: COMPRA | D8: 0.86 | E8: 34.965 | F8: 0 | G8: =(E8*D8)+F8 -> 30.0699
B9: 45595 | C9: COMPRA | D9: 2.9444 | E9: 39.055 | F9: 0 | G9: =(E9*D9)+F9 -> 114.99354
B10: 45628 | C10: COMPRA | D10: 1.304 | E10: 41.405 | F10: 0 | G10: =(E10*D10)+F10 -> 53.99212 | I10: Qtde Comprada | J10: =SUMIFS(D4:D21,C4:C21,"COMPRA") -> 32.423903
B11: 45667 | C11: COMPRA | D11: 2.0372131 | E11: 36.815 | F11: 0 | G11: 75 | I11: Qtde Vendida | J11: =SUMIFS(D4:D21,C4:C21,"VENDA") -> 0
B12: 45758 | C12: COMPRA | D12: 1.2628451 | E12: 40.385 | F12: 0 | G12: 51 | I12: Qtde em Carteira | J12: =J10-J11 -> 32.423903
B13: 45848 | C13: COMPRA | D13: 5.4997718 | E13: 43.82 | F13: 0 | G13: =(E13*D13)+F13 -> 241 | I13: Valor das Compras | J13: =SUMIFS(G4:G21,C4:C21,"COMPRA") -> 1271.7886
B14: 45939 | C14: COMPRA | D14: 1.3020277 | E14: 46.85 | F14: 0 | G14: =(E14*D14)+F14 -> 61 | I14: Valor das Vendas | J14: =SUMIFS(E4:E21,C4:C21,"VENDA") -> 0
B15: 46000 | C15: COMPRA | D15: 2.2178413 | E15: 40.58 | F15: 0 | G15: =(E15*D15)+F15 -> 90 | I15: Total de Taxas | J15: =SUM(F4:F21) -> 0.3
B16: 46051 | C16: COMPRA | D16: 2.211083 | E16: 43.49 | F16: 0 | G16: =(E16*D16)+F16 -> 96.16 | I16: Preço Médio | J16: =IF(J10<>0,((J13+J15)/J10),"") -> 39.233049
B17: 46087 | C17: COMPRA | D17: 2.3455452 | E17: 46.13 | F17: 0 | G17: =(E17*D17)+F17 -> 108.2
B18: 46205 | C18: COMPRA | D18: 2.6391753 | E18: 48.5 | F18: 0 | G18: =(E18*D18)+F18 -> 128
G19: =(E19*D19)+F19 -> 0
G20: =(E20*D20)+F20 -> 0
G21: =(E21*D21)+F21 -> 0

Sheet KO
B2: ID | C2: KO | D2: Nome do Ativo | F2: =IFERROR(__xludf.DUMMYFUNCTION("IF(C2="""","""",GOOGLEFINANCE(C2,""Name""))"),"Coca-Cola Co") -> Coca-Cola Co
B3: Data | C3: Operação | D3: Qtde | E3: Valor unitário | F3: Taxas/Impostos | G3: Valor da operação | H3: Gráfico | K3: Dias graf
B4: 44630 | C4: COMPRA | D4: 1 | E4: 57.57 | F4: 0 | G4: =E4*D4 -> 57.57 | H4: =IFERROR(__xludf.DUMMYFUNCTION("IF(C2="""","""",SPARKLINE(GOOGLEFINANCE(C2,""price"",TODAY()-K4,TODAY())))"),"") | K4: 30
B5: 44841 | C5: COMPRA | D5: 1 | E5: 54.79 | F5: 0 | G5: =E5*D5 -> 54.79
B6: 45246 | C6: COMPRA | D6: 1.9888033 | E6: 57.16 | F6: 0 | G6: =E6*D6 -> 113.68
B7: 45595 | C7: COMPRA | D7: 1.7008134 | E7: 66.42 | F7: 0 | G7: =E7*D7 -> 112.96802
B8: 45628 | C8: COMPRA | D8: 0.85027586 | E8: 63.49 | F8: 0 | G8: =E8*D8 -> 53.984014
B9: 45667 | C9: COMPRA | D9: =G9/E9 -> 1.2135922 | E9: 61.8 | F9: 0 | G9: 75
B10: 45758 | C10: COMPRA | D10: =G10/E10 -> 0.71149554 | E10: 71.68 | F10: 0 | G10: 51 | I10: Qtde Comprada | J10: =SUMIFS(D4:D21,C4:C21,"COMPRA") -> 19.252848
B11: 45848 | C11: COMPRA | D11: 3.4234753 | E11: 69.52 | F11: 0 | G11: =E11*D11 -> 238 | I11: Qtde Vendida | J11: =SUMIFS(D4:D21,C4:C21,"VENDA") -> 0
B12: 45939 | C12: COMPRA | D12: 0.9141801 | E12: 66.77 | F12: 0 | G12: =E12*D12 -> 61.039805 | I12: Qtde em Carteira | J12: =J10-J11 -> 19.252848
B13: 45939 | C13: COMPRA | D13: 0.91442208 | E13: 66.77 | F13: 0 | G13: =E13*D13 -> 61.055962 | I13: Valor das Compras | J13: =SUMIFS(G4:G21,C4:C21,"COMPRA") -> 1301.5323
B14: 46000 | C14: COMPRA | D14: 1.2838802 | E14: 70.1 | F14: 0 | G14: =E14*D14 -> 90 | I14: Valor das Vendas | J14: =SUMIFS(E4:E21,C4:C21,"VENDA") -> 0
B15: 46051 | C15: COMPRA | D15: 1.3038644 | E15: 73.75 | F15: 0 | G15: =E15*D15 -> 96.16 | I15: Total de Taxas | J15: =SUM(F4:F21) -> 0
B16: 46087 | C16: COMPRA | D16: 1.4099542 | E16: 76.8 | F16: 0 | G16: =E16*D16 -> 108.28448 | I16: Preço Médio | J16: =IF(J10<>0,((J13+J15)/J10),"") -> 67.602064
B17: 46205 | C17: COMPRA | D17: 1.5380918 | E17: 83.22 | F17: 0 | G17: =E17*D17 -> 128
G18: =E18*D18 -> 0
G19: =E19*D19 -> 0
G20: =E20*D20 -> 0
G21: =E21*D21 -> 0

Sheet APH
B2: ID | C2: APH | D2: Nome do Ativo | F2: =IFERROR(__xludf.DUMMYFUNCTION("IF(C2="""","""",GOOGLEFINANCE(C2,""Name""))"),"Amphenol Corp") -> Amphenol Corp
B3: Data | C3: Operação | D3: Qtde | E3: Valor unitário | F3: Taxas/Impostos | G3: Valor da operação | H3: Gráfico | K3: Dias graf
B4: 44630 | C4: COMPRA | D4: 2 | E4: 18.035 | F4: 0 | G4: =E4*D4 -> 36.07 | H4: =IFERROR(__xludf.DUMMYFUNCTION("IF(C2="""","""",SPARKLINE(GOOGLEFINANCE(C2,""price"",TODAY()-K4,TODAY())))"),"") | K4: 30
B5: 45248 | C5: COMPRA | D5: 2 | E5: 22.505 | F5: 0 | G5: =E5*D5 -> 45.01
B6: 45505 | C6: COMPRA | D6: 2.001909 | E6: 31.46 | F6: 0 | G6: =E6*D6 -> 62.980057
B7: 45551 | C7: COMPRA | D7: 0.94652152 | E7: 31.685 | F7: 0 | G7: =E7*D7 -> 29.990534
B8: 45595 | C8: COMPRA | D8: 3.3046347 | E8: 34.195 | F8: 0 | G8: =E8*D8 -> 113.00198
B9: 45628 | C9: COMPRA | D9: 1.461101 | E9: 36.915 | F9: 0 | G9: =E9*D9 -> 53.936543
B10: 45667 | C10: COMPRA | D10: 2.050581 | E10: 36.575 | F10: 0 | G10: 75 | I10: Qtde Comprada | J10: =SUMIFS(D4:D21,C4:C21,"COMPRA") -> 27.644698
B11: 45758 | C11: COMPRA | D11: 1.5641773 | E11: 32.605 | F11: 0 | G11: 51 | I11: Qtde Vendida | J11: =SUMIFS(D4:D21,C4:C21,"VENDA") -> 0
B12: 45848 | C12: COMPRA | D12: 4.9175729 | E12: 49.195 | F12: 0 | G12: =E12*D12 -> 241.92 | I12: Qtde em Carteira | J12: =J10-J11 -> 27.644698
B13: 46000 | C13: COMPRA | D13: 1.2997328 | E13: 69.245 | F13: 0 | G13: =E13*D13 -> 90.000001 | I13: Valor das Compras | J13: =SUMIFS(G4:G21,C4:C21,"COMPRA") -> 1263.2948
B14: 46051 | C14: COMPRA | D14: 1.2780221 | E14: 75.03 | F14: 0 | G14: =E14*D14 -> 95.89 | I14: Valor das Vendas | J14: =SUMIFS(E4:E21,C4:C21,"VENDA") -> 0
B15: 46087 | C15: COMPRA | D15: 1.6236495 | E15: 66.64 | F15: 0 | G15: =E15*D15 -> 108.2 | I15: Total de Taxas | J15: =SUM(F4:F21) -> 0
B16: 46205 | C16: COMPRA | D16: 1.5725782 | E16: 81.335 | F16: 0 | G16: =E16*D16 -> 127.90564 | I16: Preço Médio | J16: =IF(J10<>0,((J13+J15)/J10),"") -> 45.697543
B17: 46209 | C17: COMPRA | D17: 1.6242179 | E17: 81.51 | F17: 0 | G17: =E17*D17 -> 132.39
G18: =E18*D18 -> 0
G19: =E19*D19 -> 0
G20: =E20*D20 -> 0
G21: =E21*D21 -> 0

Sheet EGIE3
B2: ID | C2: EGIE3 | D2: Nome do Ativo | F2: =IFERROR(__xludf.DUMMYFUNCTION("IF(C2="""","""",GOOGLEFINANCE(C2,""Name""))"),"Engie Brasil Energia SA") -> Engie Brasil Energia SA
B3: Data | C3: Operação | D3: Qtde | E3: Valor unitário | F3: Taxas/Impostos | G3: Valor da operação | H3: Gráfico | K3: Dias graf
B4: 44628 | C4: COMPRA | D4: 4.2 | E4: 27.93 | F4: 0 | G4: =E4*D4 -> 117.306 | H4: =IFERROR(__xludf.DUMMYFUNCTION("IF(C2="""","""",SPARKLINE(GOOGLEFINANCE(C2,""price"",TODAY()-K4,TODAY())))"),"") | K4: 60
B5: 44655 | C5: COMPRA | D5: 7 | E5: 31.26 | F5: 0 | G5: =E5*D5 -> 218.82
B6: 44841 | C6: COMPRA | D6: 4.2 | E6: 27.71 | F6: 0 | G6: =E6*D6 -> 116.382
B7: 44935 | C7: COMPRA | D7: 4.2 | E7: 27.11 | F7: 0 | G7: =E7*D7 -> 113.862
B8: 44999 | C8: COMPRA | D8: 11.2 | E8: 29.74 | F8: 0 | G8: =E8*D8 -> 333.088
B9: 45246 | C9: COMPRA | D9: 5.6 | E9: 31.04 | F9: 0 | G9: =E9*D9 -> 173.824
B10: 45300 | C10: COMPRA | D10: 4.2 | E10: 31.35 | F10: 0 | G10: =E10*D10 -> 131.67 | I10: Qtde Comprada | J10: =SUMIFS(D4:D28,C4:C28,"COMPRA") -> 161
B11: 45341 | C11: COMPRA | D11: 7 | E11: 29.44 | F11: 0 | G11: =E11*D11 -> 206.08 | I11: Qtde Vendida | J11: =SUMIFS(D4:D28,C4:C28,"VENDA") -> 0
B12: 45453 | C12: COMPRA | D12: 5.6 | E12: 31.02 | F12: 0 | G12: =E12*D12 -> 173.712 | I12: Qtde em Carteira | J12: =J10-J11 -> 161
B13: 45505 | C13: COMPRA | D13: 4.2 | E13: 31.71 | F13: 0 | G13: =E13*D13 -> 133.182 | I13: Valor das Compras | J13: =SUMIFS(G4:G28,C4:C28,"COMPRA") -> 4814.718
B14: 45551 | C14: COMPRA | D14: 4.2 | E14: 31.64 | F14: 0 | G14: =E14*D14 -> 132.888 | I14: Valor das Vendas | J14: =SUMIFS(E4:E28,C4:C28,"VENDA") -> 0
B15: 45595 | C15: COMPRA | D15: 21 | E15: 29.44 | F15: 0 | G15: =E15*D15 -> 618.24 | I15: Total de Taxas | J15: =SUM(F4:F28) -> 0
B16: 45628 | C16: COMPRA | D16: 5.6 | E16: 26.71 | F16: 0 | G16: =E16*D16 -> 149.576 | I16: Preço Médio | J16: =IF(J10<>0,((J13+J15)/J10),"") -> 29.905081
B17: 45667 | C17: COMPRA | D17: 8.4 | E17: 25.16 | F17: 0 | G17: =E17*D17 -> 211.344
B18: 45758 | C18: COMPRA | D18: 4.2 | E18: 28.22 | F18: 0 | G18: =E18*D18 -> 118.524
B19: 45848 | C19: COMPRA | D19: 8.4 | E19: 30 | F19: 0 | G19: =E19*D19 -> 252
B20: 45922 | C20: COMPRA | D20: 8.4 | E20: 29.74 | F20: 0 | G20: =E20*D20 -> 249.816
B21: 45939 | C21: COMPRA | D21: 8.4 | E21: 28.46 | F21: 0 | G21: =E21*D21 -> 239.064
B22: 46000 | C22: COMPRA | D22: 7 | E22: 30.4 | F22: 0 | G22: =E22*D22 -> 212.8
B23: 46051 | C23: COMPRA | D23: 8 | E23: 33.38 | F23: 0 | G23: =E23*D23 -> 267.04
B24: 46087 | C24: COMPRA | D24: 10 | E24: 31.85 | F24: 0 | G24: =E24*D24 -> 318.5
B25: 46205 | C25: COMPRA | D25: 10 | E25: 32.7 | F25: 0 | G25: =E25*D25 -> 327

Sheet KNRI11
B2: ID | C2: KNRI11 | D2: Nome do Ativo | F2: =IFERROR(__xludf.DUMMYFUNCTION("IF(C2="""","""",GOOGLEFINANCE(C2,""Name""))"),"Kinea Renda Imobiliaria FII") -> Kinea Renda Imobiliaria FII
B3: Data | C3: Operação | D3: Qtde | E3: Valor unitário | F3: Taxas/Impostos | G3: Valor da operação | H3: Gráfico | K3: Dias graf
B4: 44628 | C4: COMPRA | D4: 1 | E4: 130.38 | F4: 0 | G4: =E4*D4 -> 130.38 | H4: =IFERROR(__xludf.DUMMYFUNCTION("IF(C2="""","""",SPARKLINE(GOOGLEFINANCE(C2,""price"",TODAY()-K4,TODAY())))"),"") | K4: 30
B5: 44743 | C5: COMPRA | D5: 1 | E5: 130.59 | F5: 0 | G5: =E5*D5 -> 130.59
B6: 44841 | C6: COMPRA | D6: 1 | E6: 152.84 | F6: 0 | G6: =E6*D6 -> 152.84
B7: 44935 | C7: COMPRA | D7: 1 | E7: 138.69 | F7: 0 | G7: =E7*D7 -> 138.69
B8: 44999 | C8: COMPRA | D8: 2 | E8: 137.51 | F8: 0 | G8: =E8*D8 -> 275.02
B9: 45300 | C9: COMPRA | D9: 1 | E9: 164.38 | F9: 0 | G9: =E9*D9 -> 164.38
B10: 45341 | C10: COMPRA | D10: 2 | E10: 136.65 | F10: 0 | G10: =E10*D10 -> 273.3 | I10: Qtde Comprada | J10: =SUMIFS(D4:D25,C4:C25,"COMPRA") -> 30
B11: 45426 | C11: COMPRA | D11: 1 | E11: 160.7 | F11: 0 | G11: =E11*D11 -> 160.7 | I11: Qtde Vendida | J11: =SUMIFS(D4:D25,C4:C25,"VENDA") -> 0
B12: 45453 | C12: COMPRA | D12: 1 | E12: 157.84 | F12: 0 | G12: =E12*D12 -> 157.84 | I12: Qtde em Carteira | J12: =J10-J11 -> 30
B13: 45505 | C13: COMPRA | D13: 1 | E13: 154.6 | F13: 0 | G13: =E13*D13 -> 154.6 | I13: Valor das Compras | J13: =SUMIFS(G4:G25,C4:C25,"COMPRA") -> 4371.3
B14: 45551 | C14: COMPRA | D14: 1 | E14: 148.29 | F14: 0 | G14: =E14*D14 -> 148.29 | I14: Valor das Vendas | J14: =SUMIFS(E4:E25,C4:C25,"VENDA") -> 0
B15: 45595 | C15: COMPRA | D15: 4 | E15: 138.55 | F15: 0 | G15: =E15*D15 -> 554.2 | I15: Total de Taxas | J15: =SUM(F4:F25) -> 0
B16: 45628 | C16: COMPRA | D16: 1 | E16: 131.2 | F16: 0 | G16: =E16*D16 -> 131.2 | I16: Preço Médio | J16: =IF(J10<>0,((J13+J15)/J10),"") -> 145.71
B17: 45667 | C17: COMPRA | D17: 1 | E17: 133.74 | F17: 0 | G17: =E17*D17 -> 133.74
B18: 45758 | C18: COMPRA | D18: 1 | E18: 134.77 | F18: 0 | G18: =E18*D18 -> 134.77
B19: 45848 | C19: COMPRA | D19: 2 | E19: 143.83 | F19: 0 | G19: =E19*D19 -> 287.66
B20: 45922 | C20: COMPRA | D20: 1 | E20: 147.79 | F20: 0 | G20: =E20*D20 -> 147.79
B21: 45939 | C21: COMPRA | D21: 2 | E21: 144.43 | F21: 0 | G21: =E21*D21 -> 288.86
B22: 46051 | C22: COMPRA | D22: 1 | E22: 162.01 | F22: 0 | G22: =E22*D22 -> 162.01
B23: 46087 | C23: COMPRA | D23: 2 | E23: 167.1 | F23: 0 | G23: =E23*D23 -> 334.2
B24: 46205 | C24: COMPRA | D24: 2 | E24: 155.12 | F24: 0 | G24: =E24*D24 -> 310.24

Sheet HGRU11
B2: ID | C2: HGRU11 | D2: Nome do Ativo | F2: =IFERROR(__xludf.DUMMYFUNCTION("IF(C2="""","""",GOOGLEFINANCE(C2,""Name""))"),"Patria Renda Urbana FII RL Unica") -> Patria Renda Urbana FII RL Unica
B3: Data | C3: Operação | D3: Qtde | E3: Valor unitário | F3: Taxas/Impostos | G3: Valor da operação | H3: Gráfico | K3: Dias graf
B4: 44628 | C4: COMPRA | D4: 1 | E4: 110.99 | F4: 0 | G4: =E4*D4 -> 110.99 | H4: =IFERROR(__xludf.DUMMYFUNCTION("IF(C2="""","""",SPARKLINE(GOOGLEFINANCE(C2,""price"",TODAY()-K4,TODAY())))"),"") | K4: 30
B5: 44655 | C5: COMPRA | D5: 1 | E5: 113.79 | F5: 0 | G5: =E5*D5 -> 113.79
B6: 44841 | C6: COMPRA | D6: 1 | E6: 126.14 | F6: 0 | G6: =E6*D6 -> 126.14
B7: 44935 | C7: COMPRA | D7: 1 | E7: 117.35 | F7: 0 | G7: =E7*D7 -> 117.35
B8: 44999 | C8: COMPRA | D8: 3 | E8: 115.58 | F8: 0 | G8: =E8*D8 -> 346.74
B9: 45246 | C9: COMPRA | D9: 1 | E9: 130.49 | F9: 0 | G9: =E9*D9 -> 130.49
B10: 45300 | C10: COMPRA | D10: 3 | E10: 137.78 | F10: 0 | G10: =E10*D10 -> 413.34 | I10: Qtde Comprada | J10: =SUMIFS(D4:D26,C4:C26,"COMPRA") -> 39
B11: 45426 | C11: COMPRA | D11: 1 | E11: 129.65 | F11: 0 | G11: =E11*D11 -> 129.65 | I11: Qtde Vendida | J11: =SUMIFS(D4:D26,C4:C26,"VENDA") -> 0
B12: 45453 | C12: COMPRA | D12: 1 | E12: 127.92 | F12: 0 | G12: =E12*D12 -> 127.92 | I12: Qtde em Carteira | J12: =J10-J11 -> 39
B13: 45505 | C13: COMPRA | D13: 1 | E13: 126.77 | F13: 0 | G13: =E13*D13 -> 126.77 | I13: Valor das Compras | J13: =SUMIFS(G4:G26,C4:C26,"COMPRA") -> 4852.01
B14: 45551 | C14: COMPRA | D14: 1 | E14: 124.91 | F14: 0 | G14: =E14*D14 -> 124.91 | I14: Valor das Vendas | J14: =SUMIFS(E4:E26,C4:C26,"VENDA") -> 0
B15: 45595 | C15: COMPRA | D15: 5 | E15: 122.65 | F15: 0 | G15: =E15*D15 -> 613.25 | I15: Total de Taxas | J15: =SUM(F4:F26) -> 0
B16: 45628 | C16: COMPRA | D16: 1 | E16: 114.75 | F16: 0 | G16: =E16*D16 -> 114.75 | I16: Preço Médio | J16: =IF(J10<>0,((J13+J15)/J10),"") -> 124.41051
B17: 45667 | C17: COMPRA | D17: 2 | E17: 114.42 | F17: 0 | G17: =E17*D17 -> 228.84
B18: 45758 | C18: COMPRA | D18: 1 | E18: 115.11 | F18: 0 | G18: =E18*D18 -> 115.11
B19: 45848 | C19: COMPRA | D19: 2 | E19: 124.32 | F19: 0 | G19: =E19*D19 -> 248.64
B20: 45922 | C20: COMPRA | D20: 2 | E20: 126.84 | F20: 0 | G20: =E20*D20 -> 253.68
B21: 45939 | C21: COMPRA | D21: 2 | E21: 125.91 | F21: 0 | G21: =E21*D21 -> 251.82
B22: 46000 | C22: COMPRA | D22: 2 | E22: 127.61 | F22: 0 | G22: =E22*D22 -> 255.22
B23: 46051 | C23: COMPRA | D23: 2 | E23: 127.12 | F23: 0 | G23: =E23*D23 -> 254.24
B24: 46087 | C24: COMPRA | D24: 2 | E24: 129.86 | F24: 0 | G24: =E24*D24 -> 259.72
B25: 46205 | C25: COMPRA | D25: 3 | E25: 129.55 | F25: 0 | G25: =E25*D25 -> 388.65

Sheet HGLG11
B2: ID | C2: HGLG11 | D2: Nome do Ativo | F2: =IFERROR(__xludf.DUMMYFUNCTION("IF(C2="""","""",GOOGLEFINANCE(C2,""Name""))"),"Patria Log FII RL") -> Patria Log FII RL
B3: Data | C3: Operação | D3: Qtde | E3: Valor unitário | F3: Taxas/Impostos | G3: Valor da operação | H3: Gráfico | K3: Dias graf
B4: 44628 | C4: COMPRA | D4: 1 | E4: 161.5 | F4: 0 | G4: =E4*D4 -> 161.5 | H4: =IFERROR(__xludf.DUMMYFUNCTION("IF(C2="""","""",SPARKLINE(GOOGLEFINANCE(C2,""price"",TODAY()-K4,TODAY())))"),"") | K4: 30
B5: 44743 | C5: COMPRA | D5: 1 | E5: 161.15 | F5: 0 | G5: =E5*D5 -> 161.15
B6: 44841 | C6: COMPRA | D6: 1 | E6: 168.68 | F6: 0 | G6: =E6*D6 -> 168.68
B7: 44999 | C7: COMPRA | D7: 2 | E7: 160.2 | F7: 0 | G7: =E7*D7 -> 320.4
B8: 45246 | C8: COMPRA | D8: 1 | E8: 160.01 | F8: 0 | G8: =E8*D8 -> 160.01
B9: 45300 | C9: COMPRA | D9: 1 | E9: 162.1 | F9: 0 | G9: =E9*D9 -> 162.1
B10: 45341 | C10: COMPRA | D10: 1 | E10: 165.6 | F10: 0 | G10: =E10*D10 -> 165.6 | I10: Qtde Comprada | J10: =SUMIFS(D4:D26,C4:C26,"COMPRA") -> 28
B11: 45426 | C11: COMPRA | D11: 1 | E11: 161.59 | F11: 0 | G11: =E11*D11 -> 161.59 | I11: Qtde Vendida | J11: =SUMIFS(D4:D26,C4:C26,"VENDA") -> 0
B12: 45453 | C12: COMPRA | D12: 1 | E12: 160 | F12: 0 | G12: =E12*D12 -> 160 | I12: Qtde em Carteira | J12: =J10-J11 -> 28
B13: 45505 | C13: COMPRA | D13: 1 | E13: 159.41 | F13: 0 | G13: =E13*D13 -> 159.41 | I13: Valor das Compras | J13: =SUMIFS(G4:G26,C4:C26,"COMPRA") -> 4422.38
B14: 45551 | C14: COMPRA | D14: 1 | E14: 160.23 | F14: 0 | G14: =E14*D14 -> 160.23 | I14: Valor das Vendas | J14: =SUMIFS(E4:E26,C4:C26,"VENDA") -> 0
B15: 45595 | C15: COMPRA | D15: 4 | E15: 155.54 | F15: 0 | G15: =E15*D15 -> 622.16 | I15: Total de Taxas | J15: =SUM(F4:F26) -> 0
B16: 45628 | C16: COMPRA | D16: 1 | E16: 150.07 | F16: 0 | G16: =E16*D16 -> 150.07 | I16: Preço Médio | J16: =IF(J10<>0,((J13+J15)/J10),"") -> 157.94214
B17: 45667 | C17: COMPRA | D17: 1 | E17: 151.01 | F17: 0 | G17: =E17*D17 -> 151.01
B18: 45758 | C18: COMPRA | D18: 1 | E18: 152.33 | F18: 0 | G18: =E18*D18 -> 152.33
B19: 45848 | C19: COMPRA | D19: 1 | E19: 154.98 | F19: 0 | G19: =E19*D19 -> 154.98
B20: 45922 | C20: COMPRA | D20: 1 | E20: 159.17 | F20: 0 | G20: =E20*D20 -> 159.17
B21: 45939 | C21: COMPRA | D21: 1 | E21: 159.72 | F21: 0 | G21: =E21*D21 -> 159.72
B22: 46000 | C22: COMPRA | D22: 1 | E22: 159.24 | F22: 0 | G22: =E22*D22 -> 159.24
B23: 46051 | C23: COMPRA | D23: 1 | E23: 157.63 | F23: 0 | G23: =E23*D23 -> 157.63
B24: 46087 | C24: COMPRA | D24: 2 | E24: 158.42 | F24: 0 | G24: =E24*D24 -> 316.84
B25: 02/07/1016 | C25: COMPRA | D25: 2 | E25: 149.28 | F25: 0 | G25: =E25*D25 -> 298.56

Sheet VISC11
B2: ID | C2: VISC11 | D2: Nome do Ativo | F2: =IFERROR(__xludf.DUMMYFUNCTION("IF(C2="""","""",GOOGLEFINANCE(C2,""Name""))"),"Vinci Shopping Centers FI Imobiliario") -> Vinci Shopping Centers FI Imobiliario
B3: Data | C3: Operação | D3: Qtde | E3: Valor unitário | F3: Taxas/Impostos | G3: Valor da operação | H3: Gráfico | K3: Dias graf
B4: 44628 | C4: COMPRA | D4: 1 | E4: 98.73 | F4: 0 | G4: =E4*D4 -> 98.73 | H4: =IFERROR(__xludf.DUMMYFUNCTION("IF(C2="""","""",SPARKLINE(GOOGLEFINANCE(C2,""price"",TODAY()-K4,TODAY())))"),"") | K4: 30
B5: 44655 | C5: COMPRA | D5: 1 | E5: 100.33 | F5: 0 | G5: =E5*D5 -> 100.33
B6: 44841 | C6: COMPRA | D6: 2 | E6: 112.6 | F6: 0 | G6: =E6*D6 -> 225.2
B7: 44935 | C7: COMPRA | D7: 1 | E7: 104.89 | F7: 0 | G7: =E7*D7 -> 104.89
B8: 44999 | C8: COMPRA | D8: 3 | E8: 102.68 | F8: 0 | G8: =E8*D8 -> 308.04
B9: 45246 | C9: COMPRA | D9: 1 | E9: 119.75 | F9: 0 | G9: =E9*D9 -> 119.75
B10: 45300 | C10: COMPRA | D10: 1 | E10: 120.39 | F10: 0 | G10: =E10*D10 -> 120.39 | I10: Qtde Comprada | J10: =SUMIFS(D4:D27,C4:C27,"COMPRA") -> 42
B11: 45341 | C11: COMPRA | D11: 2 | E11: 121.57 | F11: 0 | G11: =E11*D11 -> 243.14 | I11: Qtde Vendida | J11: =SUMIFS(D4:D27,C4:C27,"VENDA") -> 0
B12: 45426 | C12: COMPRA | D12: 1 | E12: 120.64 | F12: 0 | G12: =E12*D12 -> 120.64 | I12: Qtde em Carteira | J12: =J10-J11 -> 42
B13: 45453 | C13: COMPRA | D13: 1 | E13: 115.29 | F13: 0 | G13: =E13*D13 -> 115.29 | I13: Valor das Compras | J13: =SUMIFS(G4:G27,C4:C27,"COMPRA") -> 4520.49
B14: 45505 | C14: COMPRA | D14: 1 | E14: 112.37 | F14: 0 | G14: =E14*D14 -> 112.37 | I14: Valor das Vendas | J14: =SUMIFS(E4:E27,C4:C27,"VENDA") -> 0
B15: 45551 | C15: COMPRA | D15: 1 | E15: 108.95 | F15: 0 | G15: =E15*D15 -> 108.95 | I15: Total de Taxas | J15: =SUM(F4:F27) -> 0
B16: 45595 | C16: COMPRA | D16: 6 | E16: 104.69 | F16: 0 | G16: =E16*D16 -> 628.14 | I16: Preço Médio | J16: =IF(J10<>0,((J13+J15)/J10),"") -> 107.63071
B17: 45628 | C17: COMPRA | D17: 1 | E17: 96.76 | F17: 0 | G17: =E17*D17 -> 96.76
B18: 45667 | C18: COMPRA | D18: 2 | E18: 93.81 | F18: 0 | G18: =E18*D18 -> 187.62
B19: 45758 | C19: COMPRA | D19: 1 | E19: 99.06 | F19: 0 | G19: =E19*D19 -> 99.06
B20: 45848 | C20: COMPRA | D20: 2 | E20: 103.64 | F20: 0 | G20: =E20*D20 -> 207.28
B21: 45922 | C21: COMPRA | D21: 2 | E21: 108.33 | F21: 0 | G21: =E21*D21 -> 216.66
B22: 45939 | C22: COMPRA | D22: 2 | E22: 109.03 | F22: 0 | G22: =E22*D22 -> 218.06
B23: 46000 | C23: COMPRA | D23: 2 | E23: 110.83 | F23: 0 | G23: =E23*D23 -> 221.66
B24: 46051 | C24: COMPRA | D24: 2 | E24: 108.94 | F24: 0 | G24: =E24*D24 -> 217.88
B25: 46087 | C25: COMPRA | D25: 3 | E25: 111.9 | F25: 0 | G25: =E25*D25 -> 335.7
B26: 46205 | C26: COMPRA | D26: 3 | E26: 104.65 | F26: 0 | G26: =E26*D26 -> 313.95

Sheet ITUB3
B2: ID | C2: ITUB3 | D2: Nome do Ativo | F2: =IFERROR(__xludf.DUMMYFUNCTION("IF(C2="""","""",GOOGLEFINANCE(C2,""Name""))"),"Itau Unibanco Holding Cedear") -> Itau Unibanco Holding Cedear
B3: Data | C3: Operação | D3: Qtde | E3: Valor unitário | F3: Taxas/Impostos | G3: Valor da operação | H3: Gráfico | K3: Dias graf
B4: 44628 | C4: COMPRA | D4: 5 | E4: 20.54 | F4: 0 | G4: =E4*D4 -> 102.7 | H4: =IFERROR(__xludf.DUMMYFUNCTION("IF(C2="""","""",SPARKLINE(GOOGLEFINANCE(C2,""price"",TODAY()-K4,TODAY())))"),"") | K4: 30
B5: 44655 | C5: COMPRA | D5: 5 | E5: 23.44 | F5: 0 | G5: =E5*D5 -> 117.2
B6: 44743 | C6: COMPRA | D6: 3 | E6: 19.7 | F6: 0 | G6: =E6*D6 -> 59.1
B7: 44841 | C7: COMPRA | D7: 5 | E7: 22.23 | F7: 0 | G7: =E7*D7 -> 111.15
B8: 44935 | C8: COMPRA | D8: 5 | E8: 22.11 | F8: 0 | G8: =E8*D8 -> 110.55
B9: 44999 | C9: COMPRA | D9: 15 | E9: 20.59 | F9: 0 | G9: =E9*D9 -> 308.85
B10: 45246 | C10: COMPRA | D10: 7 | E10: 25.59 | F10: 0 | G10: =E10*D10 -> 179.13 | I10: Qtde Comprada | J10: =SUMIFS(D4:D25,C4:C25,"COMPRA") -> 142
B11: 45300 | C11: COMPRA | D11: 5 | E11: 27.97 | F11: 0 | G11: =E11*D11 -> 139.85 | I11: Qtde Vendida | J11: =SUMIFS(D4:D25,C4:C25,"VENDA") -> 0
B12: 45341 | C12: COMPRA | D12: 8 | E12: 29.9 | F12: 0 | G12: =E12*D12 -> 239.2 | I12: Qtde em Carteira | J12: =J10-J11 -> 142
B13: 45453 | C13: COMPRA | D13: 5 | E13: 27.02 | F13: 0 | G13: =E13*D13 -> 135.1 | I13: Valor das Compras | J13: =SUMIFS(G4:G25,C4:C25,"COMPRA") -> 4147.78
B14: 45505 | C14: COMPRA | D14: 4 | E14: 28.88 | F14: 0 | G14: =E14*D14 -> 115.52 | I14: Valor das Vendas | J14: =SUMIFS(E4:E25,C4:C25,"VENDA") -> 0
B15: 45595 | C15: COMPRA | D15: 20 | E15: 30.41 | F15: 0 | G15: =E15*D15 -> 608.2 | I15: Total de Taxas | J15: =SUM(F4:F25) -> 0
B16: 45628 | C16: COMPRA | D16: 5 | E16: 28.19 | F16: 0 | G16: =E16*D16 -> 140.95 | I16: Preço Médio | J16: =IF(J10<>0,((J13+J15)/J10),"") -> 29.209718
B17: 45667 | C17: COMPRA | D17: 8 | E17: 27.25 | F17: 0 | G17: =E17*D17 -> 218
B18: 45758 | C18: COMPRA | D18: 5 | E18: 28.27 | F18: 0 | G18: =E18*D18 -> 141.35
B19: 45848 | C19: COMPRA | D19: 8 | E19: 31.72 | F19: 0 | G19: =E19*D19 -> 253.76
B20: 45922 | C20: COMPRA | D20: 8 | E20: 34.14 | F20: 0 | G20: =E20*D20 -> 273.12
B21: 46051 | C21: COMPRA | D21: 6 | E21: 42.66 | F21: 0 | G21: =E21*D21 -> 255.96
B22: 46087 | C22: COMPRA | D22: 8 | E22: 40.78 | F22: 0 | G22: =E22*D22 -> 326.24
B23: 46205 | C23: COMPRA | D23: 7 | E23: 44.55 | F23: 0 | G23: =E23*D23 -> 311.85

Sheet WEGE3
B2: ID | C2: WEGE3 | D2: Nome do Ativo | F2: =IFERROR(__xludf.DUMMYFUNCTION("IF(C2="""","""",GOOGLEFINANCE(C2,""Name""))"),"Weg Cedear") -> Weg Cedear
B3: Data | C3: Operação | D3: Qtde | E3: Valor unitário | F3: Taxas/Impostos | G3: Valor da operação | H3: Gráfico | K3: Dias graf
B4: 44628 | C4: COMPRA | D4: 4 | E4: 31.72 | F4: 0 | G4: =E4*D4 -> 126.88 | H4: =IFERROR(__xludf.DUMMYFUNCTION("IF(C2="""","""",SPARKLINE(GOOGLEFINANCE(C2,""price"",TODAY()-K4,TODAY())))"),"") | K4: 60
B5: 44655 | C5: COMPRA | D5: 4 | E5: 34.8 | F5: 0 | G5: =E5*D5 -> 139.2
B6: 44841 | C6: COMPRA | D6: 4 | E6: 33.54 | F6: 0 | G6: =E6*D6 -> 134.16
B7: 44999 | C7: COMPRA | D7: 8 | E7: 40.17 | F7: 0 | G7: =E7*D7 -> 321.36
B8: 45246 | C8: COMPRA | D8: 6 | E8: 33.53 | F8: 0 | G8: =E8*D8 -> 201.18
B9: 45246 | C9: COMPRA | D9: 2 | E9: 33.54 | F9: 0 | G9: =E9*D9 -> 67.08
B10: 45246 | C10: COMPRA | D10: 2 | E10: 33.47 | F10: 0 | G10: =E10*D10 -> 66.94 | I10: Qtde Comprada | J10: =SUMIFS(D4:D29,C4:C29,"COMPRA") -> 126
B11: 45300 | C11: COMPRA | D11: 3 | E11: 35.83 | F11: 0 | G11: =E11*D11 -> 107.49 | I11: Qtde Vendida | J11: =SUMIFS(D4:D29,C4:C29,"VENDA") -> 0
B12: 45341 | C12: COMPRA | D12: 7 | E12: 33.44 | F12: 0 | G12: =E12*D12 -> 234.08 | I12: Qtde em Carteira | J12: =J10-J11 -> 126
B13: 45341 | C13: COMPRA | D13: 3 | E13: 39.54 | F13: 0 | G13: =E13*D13 -> 118.62 | I13: Valor das Compras | J13: =SUMIFS(G4:G29,C4:C29,"COMPRA") -> 5295.45
B14: 45453 | C14: COMPRA | D14: 4 | E14: 37.95 | F14: 0 | G14: =E14*D14 -> 151.8 | I14: Valor das Vendas | J14: =SUMIFS(E4:E29,C4:C29,"VENDA") -> 0
B15: 45505 | C15: COMPRA | D15: 2 | E15: 51.56 | F15: 0 | G15: =E15*D15 -> 103.12 | I15: Total de Taxas | J15: =SUM(F4:F29) -> 0
B16: 45595 | C16: COMPRA | D16: 12 | E16: 53.78 | F16: 0 | G16: =E16*D16 -> 645.36 | I16: Preço Médio | J16: =IF(J10<>0,((J13+J15)/J10),"") -> 42.027381
B17: 45628 | C17: COMPRA | D17: 5 | E17: 53.9 | F17: 0 | G17: =E17*D17 -> 269.5
B18: 45667 | C18: COMPRA | D18: 4 | E18: 53.8 | F18: 0 | G18: =E18*D18 -> 215.2
B19: 45758 | C19: COMPRA | D19: 5 | E19: 45.18 | F19: 0 | G19: =E19*D19 -> 225.9
B20: 45848 | C20: COMPRA | D20: 8 | E20: 39.83 | F20: 0 | G20: =E20*D20 -> 318.64
B21: 45922 | C21: COMPRA | D21: 7 | E21: 36.67 | F21: 0 | G21: =E21*D21 -> 256.69
B22: 45939 | C22: COMPRA | D22: 12 | E22: 36.95 | F22: 0 | G22: =E22*D22 -> 443.4
B23: 46000 | C23: COMPRA | D23: 5 | E23: 47.38 | F23: 0 | G23: =E23*D23 -> 236.9
B24: 46051 | C24: COMPRA | D24: 5 | E24: 52.33 | F24: 0 | G24: =E24*D24 -> 261.65
B25: 46087 | C25: COMPRA | D25: 7 | E25: 46.63 | F25: 0 | G25: =E25*D25 -> 326.41
B26: 46205 | C26: COMPRA | D26: 7 | E26: 46.27 | F26: 0 | G26: =E26*D26 -> 323.89
G29: =E29*D29 -> 0

Sheet TAEE3
B2: ID | C2: TAEE3 | D2: Nome do Ativo | F2: =IFERROR(__xludf.DUMMYFUNCTION("IF(C2="""","""",GOOGLEFINANCE(C2,""Name""))"),"Transmissora Alianca de Enrga Eltrca S/A") -> Transmissora Alianca de Enrga Eltrca S/A
B3: Data | C3: Operação | D3: Qtde | E3: Valor unitário | F3: Taxas/Impostos | G3: Valor da operação | H3: Gráfico | K3: Dias graf
B4: 44628 | C4: COMPRA | D4: 9 | E4: 13.36 | F4: 0 | G4: =E4*D4 -> 120.24 | H4: =IFERROR(__xludf.DUMMYFUNCTION("IF(C2="""","""",SPARKLINE(GOOGLEFINANCE(C2,""price"",TODAY()-K4,TODAY())))"),"") | K4: 30
B5: 44743 | C5: COMPRA | D5: 14 | E5: 13.19 | F5: 0 | G5: =E5*D5 -> 184.66
B6: 44841 | C6: COMPRA | D6: 9 | E6: 13.26 | F6: 0 | G6: =E6*D6 -> 119.34
B7: 44935 | C7: COMPRA | D7: 8 | E7: 11.98 | F7: 0 | G7: =E7*D7 -> 95.84
B8: 44999 | C8: COMPRA | D8: 25 | E8: 12.23 | F8: 0 | G8: =E8*D8 -> 305.75
B9: 45246 | C9: COMPRA | D9: 16 | E9: 12.08 | F9: 0 | G9: =E9*D9 -> 193.28
B10: 45300 | C10: COMPRA | D10: 10 | E10: 12.38 | F10: 0 | G10: =E10*D10 -> 123.8 | I10: Qtde Comprada | J10: =SUMIFS(D4:D30,C4:C30,"COMPRA") -> 406
B11: 45341 | C11: COMPRA | D11: 20 | E11: 11.72 | F11: 0 | G11: =E11*D11 -> 234.4 | I11: Qtde Vendida | J11: =SUMIFS(D4:D30,C4:C30,"VENDA") -> 0
B12: 45426 | C12: COMPRA | D12: 8 | E12: 11.55 | F12: 0 | G12: =E12*D12 -> 92.4 | I12: Qtde em Carteira | J12: =J10-J11 -> 406
B13: 45453 | C13: COMPRA | D13: 14 | E13: 11.16 | F13: 0 | G13: =E13*D13 -> 156.24 | I13: Valor das Compras | J13: =SUMIFS(G4:G30,C4:C30,"COMPRA") -> 4955.09
B14: 45505 | C14: COMPRA | D14: 11 | E14: 11.32 | F14: 0 | G14: =E14*D14 -> 124.52 | I14: Valor das Vendas | J14: =SUMIFS(E4:E30,C4:C30,"VENDA") -> 0
B15: 45551 | C15: COMPRA | D15: 13 | E15: 11.72 | F15: 0 | G15: =E15*D15 -> 152.36 | I15: Total de Taxas | J15: =SUM(F4:F30) -> 0
B16: 45595 | C16: COMPRA | D16: 53 | E16: 11.48 | F16: 0 | G16: =E16*D16 -> 608.44 | I16: Preço Médio | J16: =IF(J10<>0,((J13+J15)/J10),"") -> 12.204655
B17: 45628 | C17: COMPRA | D17: 14 | E17: 11.28 | F17: 0 | G17: =E17*D17 -> 157.92
B18: 45667 | C18: COMPRA | D18: 19 | E18: 10.89 | F18: 0 | G18: =E18*D18 -> 206.91
B19: 45758 | C19: COMPRA | D19: 12 | E19: 11.32 | F19: 0 | G19: =E19*D19 -> 135.84
B20: 45848 | C20: COMPRA | D20: 24 | E20: 11.32 | F20: 0 | G20: =E20*D20 -> 271.68
B21: 45922 | C21: COMPRA | D21: 22 | E21: 11.83 | F21: 0 | G21: =E21*D21 -> 260.26
B22: 45939 | C22: COMPRA | D22: 19 | E22: 11.97 | F22: 0 | G22: =E22*D22 -> 227.43
B23: 46000 | C23: COMPRA | D23: 17 | E23: 13.65 | F23: 0 | G23: =E23*D23 -> 232.05
B24: 46051 | C24: COMPRA | D24: 19 | E24: 14.03 | F24: 0 | G24: =E24*D24 -> 266.57
B25: 46087 | C25: COMPRA | D25: 24 | E25: 14.01 | F25: 0 | G25: =E25*D25 -> 336.24
B26: 46205 | C26: COMPRA | D26: 26 | E26: 13.42 | F26: 0 | G26: =E26*D26 -> 348.92

Sheet PSSA3
B2: ID | C2: PSSA3 | D2: Nome do Ativo | F2: =IFERROR(__xludf.DUMMYFUNCTION("IF(C2="""","""",GOOGLEFINANCE(C2,""Name""))"),"Porto Seguro SA") -> Porto Seguro SA
B3: Data | C3: Operação | D3: Qtde | E3: Valor unitário | F3: Taxas/Impostos | G3: Valor da operação | H3: Gráfico | K3: Dias graf
B4: 44628 | C4: COMPRA | D4: 6 | E4: 19.68 | F4: 0 | G4: =E4*D4 -> 118.08 | H4: =IFERROR(__xludf.DUMMYFUNCTION("IF(C2="""","""",SPARKLINE(GOOGLEFINANCE(C2,""price"",TODAY()-K4,TODAY())))"),"") | K4: 30
B5: 44655 | C5: COMPRA | D5: 4 | E5: 20.86 | F5: 0 | G5: =E5*D5 -> 83.44
B6: 44743 | C6: COMPRA | D6: 5 | E6: 18.04 | F6: 0 | G6: =E6*D6 -> 90.2
B7: 44841 | C7: COMPRA | D7: 5 | E7: 21.27 | F7: 0 | G7: =E7*D7 -> 106.35
B8: 44999 | C8: COMPRA | D8: 12 | E8: 24.89 | F8: 0 | G8: =E8*D8 -> 298.68
B9: 45246 | C9: COMPRA | D9: 7 | E9: 28.22 | F9: 0 | G9: =E9*D9 -> 197.54
B10: 45300 | C10: COMPRA | D10: 5 | E10: 28.54 | F10: 0 | G10: =E10*D10 -> 142.7 | I10: Qtde Comprada | J10: =SUMIFS(D4:D28,C4:C28,"COMPRA") -> 120
B11: 45341 | C11: COMPRA | D11: 14 | E11: 26.1 | F11: 0 | G11: =E11*D11 -> 365.4 | I11: Qtde Vendida | J11: =SUMIFS(D4:D28,C4:C28,"VENDA") -> 0
B12: 45453 | C12: COMPRA | D12: 5 | E12: 29.74 | F12: 0 | G12: =E12*D12 -> 148.7 | I12: Qtde em Carteira | J12: =J10-J11 -> 120
B13: 45505 | C13: COMPRA | D13: 3 | E13: 30.75 | F13: 0 | G13: =E13*D13 -> 92.25 | I13: Valor das Compras | J13: =SUMIFS(G4:G28,C4:C28,"COMPRA") -> 3979.35
B14: 45595 | C14: COMPRA | D14: 16 | E14: 38.75 | F14: 0 | G14: =E14*D14 -> 620 | I14: Valor das Vendas | J14: =SUMIFS(E4:E28,C4:C28,"VENDA") -> 0
B15: 45628 | C15: COMPRA | D15: 4 | E15: 37.52 | F15: 0 | G15: =E15*D15 -> 150.08 | I15: Total de Taxas | J15: =SUM(F4:F28) -> 0
B16: 45667 | C16: COMPRA | D16: 6 | E16: 36.4 | F16: 0 | G16: =E16*D16 -> 218.4 | I16: Preço Médio | J16: =IF(J10<>0,((J13+J15)/J10),"") -> 33.16125
B17: 45758 | C17: COMPRA | D17: 5 | E17: 39.18 | F17: 0 | G17: =E17*D17 -> 195.9
B18: 46000 | C18: COMPRA | D18: 5 | E18: 48.64 | F18: 0 | G18: =E18*D18 -> 243.2
B19: 46051 | C19: COMPRA | D19: 5 | E19: 49.44 | F19: 0 | G19: =E19*D19 -> 247.2
B20: 46087 | C20: COMPRA | D20: 7 | E20: 48.81 | F20: 0 | G20: =E20*D20 -> 341.67
B21: 46205 | C21: COMPRA | D21: 6 | E21: 53.26 | F21: 0 | G21: =E21*D21 -> 319.56
G22: =E22*D22 -> 0
G23: =E23*D23 -> 0
G24: =E24*D24 -> 0
G25: =E25*D25 -> 0
G26: =E26*D26 -> 0
G27: =E27*D27 -> 0
G28: =E28*D28 -> 0

Sheet HYPE3
B2: ID | C2: HYPE3 | D2: Nome do Ativo | F2: =IFERROR(__xludf.DUMMYFUNCTION("IF(C2="""","""",GOOGLEFINANCE(C2,""Name""))"),"Hypera SA") -> Hypera SA
B3: Data | C3: Operação | D3: Qtde | E3: Valor unitário | F3: Taxas/Impostos | G3: Valor da operação | H3: Gráfico | K3: Dias graf
B4: 44628 | C4: COMPRA | D4: 3 | E4: 32.6 | F4: 0 | G4: =E4*D4 -> 97.8 | H4: =IFERROR(__xludf.DUMMYFUNCTION("IF(C2="""","""",SPARKLINE(GOOGLEFINANCE(C2,""price"",TODAY()-K4,TODAY())))"),"") | K4: 30
B5: 44743 | C5: COMPRA | D5: 3 | E5: 37.53 | F5: 0 | G5: =E5*D5 -> 112.59
B6: 44841 | C6: COMPRA | D6: 2 | E6: 46.32 | F6: 0 | G6: =E6*D6 -> 92.64
B7: 44935 | C7: COMPRA | D7: 2 | E7: 43.2 | F7: 0 | G7: =E7*D7 -> 86.4
B8: 44999 | C8: COMPRA | D8: 8 | E8: 40.58 | F8: 0 | G8: =E8*D8 -> 324.64
B9: 45246 | C9: COMPRA | D9: 5 | E9: 33.83 | F9: 0 | G9: =E9*D9 -> 169.15
B10: 45246 | C10: COMPRA | D10: 7 | E10: 34.05 | F10: 0 | G10: =E10*D10 -> 238.35 | I10: Qtde Comprada | J10: =SUMIFS(D4:D29,C4:C29,"COMPRA") -> 211
B11: 45341 | C11: COMPRA | D11: 7 | E11: 32.59 | F11: 0 | G11: =E11*D11 -> 228.13 | I11: Qtde Vendida | J11: =SUMIFS(D4:D29,C4:C29,"VENDA") -> 0
B12: 45426 | C12: COMPRA | D12: 3 | E12: 30.39 | F12: 0 | G12: =E12*D12 -> 91.17 | I12: Qtde em Carteira | J12: =J10-J11 -> 211
B13: 45453 | C13: COMPRA | D13: 6 | E13: 28.7 | F13: 0 | G13: =E13*D13 -> 172.2 | I13: Valor das Compras | J13: =SUMIFS(G4:G29,C4:C29,"COMPRA") -> 5404.46
B14: 45505 | C14: COMPRA | D14: 4 | E14: 28.47 | F14: 0 | G14: =E14*D14 -> 113.88 | I14: Valor das Vendas | J14: =SUMIFS(E4:E29,C4:C29,"VENDA") -> 0
B15: 45505 | C15: COMPRA | D15: 8 | E15: 28.33 | F15: 0 | G15: =E15*D15 -> 226.64 | I15: Total de Taxas | J15: =SUM(F4:F29) -> 0
B16: 45551 | C16: COMPRA | D16: 6 | E16: 29.02 | F16: 0 | G16: =E16*D16 -> 174.12 | I16: Preço Médio | J16: =IF(J10<>0,((J13+J15)/J10),"") -> 25.613554
B17: 45595 | C17: COMPRA | D17: 26 | E17: 24.04 | F17: 0 | G17: =E17*D17 -> 625.04
B18: 45628 | C18: COMPRA | D18: 8 | E18: 19.84 | F18: 0 | G18: =E18*D18 -> 158.72
B19: 45667 | C19: COMPRA | D19: 11 | E19: 17.93 | F19: 0 | G19: =E19*D19 -> 197.23
B20: 45758 | C20: COMPRA | D20: 7 | E20: 19.42 | F20: 0 | G20: =E20*D20 -> 135.94
B21: 45848 | C21: COMPRA | D21: 10 | E21: 26.79 | F21: 0 | G21: =E21*D21 -> 267.9
B22: 45922 | C22: COMPRA | D22: 12 | E22: 23.35 | F22: 0 | G22: =E22*D22 -> 280.2
B23: 45939 | C23: COMPRA | D23: 22 | E23: 20.82 | F23: 0 | G23: =E23*D23 -> 458.04
B24: 46000 | C24: COMPRA | D24: 9 | E24: 24.38 | F24: 0 | G24: =E24*D24 -> 219.42
B25: 46051 | C25: COMPRA | D25: 10 | E25: 25.41 | F25: 0 | G25: =E25*D25 -> 254.1
B26: 46087 | C26: COMPRA | D26: 16 | E26: 21.78 | F26: 0 | G26: =E26*D26 -> 348.48
B27: 46205 | C27: COMPRA | D27: 16 | E27: 20.73 | F27: 0 | G27: =E27*D27 -> 331.68

Sheet B3SA3
B2: ID | C2: B3SA3 | D2: Nome do Ativo | F2: =IFERROR(__xludf.DUMMYFUNCTION("IF(C2="""","""",GOOGLEFINANCE(C2,""Name""))"),"B3 SA Brasil Bolsa Balcao") -> B3 SA Brasil Bolsa Balcao
B3: Data | C3: Operação | D3: Qtde | E3: Valor unitário | F3: Taxas/Impostos | G3: Valor da operação | H3: Gráfico | K3: Dias graf
B4: 44628 | C4: COMPRA | D4: 8 | E4: 13.91 | F4: 0 | G4: =E4*D4 -> 111.28 | H4: =IFERROR(__xludf.DUMMYFUNCTION("IF(C2="""","""",SPARKLINE(GOOGLEFINANCE(C2,""price"",TODAY()-K4,TODAY())))"),"") | K4: 90
B5: 44655 | C5: COMPRA | D5: 6 | E5: 15.98 | F5: 0 | G5: =E5*D5 -> 95.88
B6: 44743 | C6: COMPRA | D6: 9 | E6: 11.26 | F6: 0 | G6: =E6*D6 -> 101.34
B7: 44841 | C7: COMPRA | D7: 8 | E7: 14.72 | F7: 0 | G7: =E7*D7 -> 117.76
B8: 44935 | C8: COMPRA | D8: 8 | E8: 12.51 | F8: 0 | G8: =E8*D8 -> 100.08
B9: 44999 | C9: COMPRA | D9: 27 | E9: 11.49 | F9: 0 | G9: =E9*D9 -> 310.23
B10: 45246 | C10: COMPRA | D10: 15 | E10: 12.96 | F10: 0 | G10: =E10*D10 -> 194.4 | I10: Qtde Comprada | J10: =SUMIFS(D4:D29,C4:C29,"COMPRA") -> 386
B11: 45300 | C11: COMPRA | D11: 9 | E11: 14.08 | F11: 0 | G11: =E11*D11 -> 126.72 | I11: Qtde Vendida | J11: =SUMIFS(D4:D29,C4:C29,"VENDA") -> 0
B12: 45341 | C12: COMPRA | D12: 18 | E12: 12.69 | F12: 0 | G12: =E12*D12 -> 228.42 | I12: Qtde em Carteira | J12: =J10-J11 -> 386
B13: 45426 | C13: COMPRA | D13: 8 | E13: 11.48 | F13: 0 | G13: =E13*D13 -> 91.84 | I13: Valor das Compras | J13: =SUMIFS(G4:G29,C4:C29,"COMPRA") -> 4818.95
B14: 45453 | C14: COMPRA | D14: 15 | E14: 10.55 | F14: 0 | G14: =E14*D14 -> 158.25 | I14: Valor das Vendas | J14: =SUMIFS(E4:E29,C4:C29,"VENDA") -> 0
B15: 45505 | C15: COMPRA | D15: 11 | E15: 11.18 | F15: 0 | G15: =E15*D15 -> 122.98 | I15: Total de Taxas | J15: =SUM(F4:F29) -> 0
B16: 45551 | C16: COMPRA | D16: 12 | E16: 12.16 | F16: 0 | G16: =E16*D16 -> 145.92 | I16: Preço Médio | J16: =IF(J10<>0,((J13+J15)/J10),"") -> 12.484326
B17: 45595 | C17: COMPRA | D17: 57 | E17: 10.78 | F17: 0 | G17: =E17*D17 -> 614.46
B18: 45628 | C18: COMPRA | D18: 17 | E18: 9.21 | F18: 0 | G18: =E18*D18 -> 156.57
B19: 45667 | C19: COMPRA | D19: 22 | E19: 10.14 | F19: 0 | G19: =E19*D19 -> 223.08
B20: 45667 | C20: COMPRA | D20: 12 | E20: 10.34 | F20: 0 | G20: =E20*D20 -> 124.08
B21: 45758 | C21: COMPRA | D21: 11 | E21: 11.94 | F21: 0 | G21: =E21*D21 -> 131.34
B22: 45922 | C22: COMPRA | D22: 19 | E22: 13.62 | F22: 0 | G22: =E22*D22 -> 258.78
B23: 45939 | C23: COMPRA | D23: 18 | E23: 12.85 | F23: 0 | G23: =E23*D23 -> 231.3
B24: 46000 | C24: COMPRA | D24: 16 | E24: 14.01 | F24: 0 | G24: =E24*D24 -> 224.16
B25: 46051 | C25: COMPRA | D25: 16 | E25: 16.38 | F25: 0 | G25: =E25*D25 -> 262.08
B26: 46087 | C26: COMPRA | D26: 20 | E26: 17 | F26: 0 | G26: =E26*D26 -> 340
B27: 46205 | C27: COMPRA | D27: 24 | E27: 14.5 | F27: 0 | G27: =E27*D27 -> 348

Sheet BBDC3
B2: ID | C2: BBDC3 | D2: Nome do Ativo | F2: =IFERROR(__xludf.DUMMYFUNCTION("IF(C2="""","""",GOOGLEFINANCE(C2,""Name""))"),"Banco Bradesco Cedear") -> Banco Bradesco Cedear
B3: Data | C3: Operação | D3: Qtde | E3: Valor unitário | F3: Taxas/Impostos | G3: Valor da operação | H3: Gráfico | K3: Dias graf
B4: 44628 | C4: COMPRA | D4: 7 | E4: 16.4 | F4: 0 | G4: =E4*D4 -> 114.8 | H4: =IFERROR(__xludf.DUMMYFUNCTION("IF(C2="""","""",SPARKLINE(GOOGLEFINANCE(C2,""price"",TODAY()-K4,TODAY())))"),"") | K4: 30
B5: 44655 | C5: COMPRA | D5: 6 | E5: 17.95 | F5: 0 | G5: =E5*D5 -> 107.7
B6: 44743 | C6: COMPRA | D6: 7 | E6: 14.46 | F6: 0 | G6: =E6*D6 -> 101.22
B7: 44841 | C7: COMPRA | D7: 5 | E7: 16.74 | F7: 0 | G7: =E7*D7 -> 83.7
B8: 44935 | C8: COMPRA | D8: 7 | E8: 13 | F8: 0 | G8: =E8*D8 -> 91
B9: 44935 | C9: COMPRA | D9: 12 | E9: 12.98 | F9: 0 | G9: =E9*D9 -> 155.76
B10: 44999 | C10: COMPRA | D10: 27 | E10: 11.7 | F10: 0 | G10: =E10*D10 -> 315.9 | I10: Qtde Comprada | J10: =SUMIFS(D4:D29,C4:C29,"COMPRA") -> 376
B11: 45246 | C11: COMPRA | D11: 14 | E11: 13.73 | F11: 0 | G11: =E11*D11 -> 192.22 | I11: Qtde Vendida | J11: =SUMIFS(D4:D29,C4:C29,"VENDA") -> 0
B12: 45300 | C12: COMPRA | D12: 9 | E12: 14.72 | F12: 0 | G12: =E12*D12 -> 132.48 | I12: Qtde em Carteira | J12: =J10-J11 -> 376
B13: 45341 | C13: COMPRA | D13: 19 | E13: 12.34 | F13: 0 | G13: =E13*D13 -> 234.46 | I13: Valor das Compras | J13: =SUMIFS(G4:G29,C4:C29,"COMPRA") -> 5116.15
B14: 45426 | C14: COMPRA | D14: 7 | E14: 11.95 | F14: 0 | G14: =E14*D14 -> 83.65 | I14: Valor das Vendas | J14: =SUMIFS(E4:E29,C4:C29,"VENDA") -> 0
B15: 45453 | C15: COMPRA | D15: 13 | E15: 11.45 | F15: 0 | G15: =E15*D15 -> 148.85 | I15: Total de Taxas | J15: =SUM(F4:F29) -> 0
B16: 45505 | C16: COMPRA | D16: 11 | E16: 11.41 | F16: 0 | G16: =E16*D16 -> 125.51 | I16: Preço Médio | J16: =IF(J10<>0,((J13+J15)/J10),"") -> 13.606782
B17: 45595 | C17: COMPRA | D17: 47 | E17: 13.19 | F17: 0 | G17: =E17*D17 -> 619.93
B18: 45628 | C18: COMPRA | D18: 14 | E18: 10.93 | F18: 0 | G18: =E18*D18 -> 153.02
B19: 45667 | C19: COMPRA | D19: 21 | E19: 10.38 | F19: 0 | G19: =E19*D19 -> 217.98
B20: 45758 | C20: COMPRA | D20: 24 | E20: 11.26 | F20: 0 | G20: =E20*D20 -> 270.24
B21: 45848 | C21: COMPRA | D21: 20 | E21: 13.83 | F21: 0 | G21: =E21*D21 -> 276.6
B22: 45922 | C22: COMPRA | D22: 18 | E22: 15.08 | F22: 0 | G22: =E22*D22 -> 271.44
B23: 45939 | C23: COMPRA | D23: 16 | E23: 14.51 | F23: 0 | G23: =E23*D23 -> 232.16
B24: 46000 | C24: COMPRA | D24: 15 | E24: 15.42 | F24: 0 | G24: =E24*D24 -> 231.3
B25: 46051 | C25: COMPRA | D25: 14 | E25: 18.38 | F25: 0 | G25: =E25*D25 -> 257.32
B26: 46087 | C26: COMPRA | D26: 21 | E26: 16.75 | F26: 0 | G26: =E26*D26 -> 351.75
B27: 46205 | C27: COMPRA | D27: 22 | E27: 15.78 | F27: 0 | G27: =E27*D27 -> 347.16

Sheet ABEV3
B2: ID | C2: ABEV3 | D2: Nome do Ativo | F2: =IFERROR(__xludf.DUMMYFUNCTION("IF(C2="""","""",GOOGLEFINANCE(C2,""Name""))"),"Amebv Cedear") -> Amebv Cedear
B3: Data | C3: Operação | D3: Qtde | E3: Valor unitário | F3: Taxas/Impostos | G3: Valor da operação | H3: Gráfico | K3: Dias graf
B4: 44628 | C4: COMPRA | D4: 8 | E4: 13.44 | F4: 0 | G4: =E4*D4 -> 107.52 | H4: =IFERROR(__xludf.DUMMYFUNCTION("IF(C2="""","""",SPARKLINE(GOOGLEFINANCE(C2,""price"",TODAY()-K4,TODAY())))"),"") | K4: 30
B5: 44655 | C5: COMPRA | D5: 5 | E5: 15.24 | F5: 0 | G5: =E5*D5 -> 76.2
B6: 44743 | C6: COMPRA | D6: 7 | E6: 13.76 | F6: 0 | G6: =E6*D6 -> 96.32
B7: 44841 | C7: COMPRA | D7: 7 | E7: 15.53 | F7: 0 | G7: =E7*D7 -> 108.71
B8: 44935 | C8: COMPRA | D8: 7 | E8: 14.39 | F8: 0 | G8: =E8*D8 -> 100.73
B9: 44999 | C9: COMPRA | D9: 22 | E9: 14.02 | F9: 0 | G9: =E9*D9 -> 308.44
B10: 45246 | C10: COMPRA | D10: 14 | E10: 13.73 | F10: 0 | G10: =E10*D10 -> 192.22 | I10: Qtde Comprada | J10: =SUMIFS(D4:D30,C4:C30,"COMPRA") -> 378
B11: 45341 | C11: COMPRA | D11: 26 | E11: 12.72 | F11: 0 | G11: =E11*D11 -> 330.72 | I11: Qtde Vendida | J11: =SUMIFS(D4:D30,C4:C30,"VENDA") -> 0
B12: 45426 | C12: COMPRA | D12: 8 | E12: 12.14 | F12: 0 | G12: =E12*D12 -> 97.12 | I12: Qtde em Carteira | J12: =J10-J11 -> 378
B13: 45453 | C13: COMPRA | D13: 13 | E13: 11.5 | F13: 0 | G13: =E13*D13 -> 149.5 | I13: Valor das Compras | J13: =SUMIFS(G4:G30,C4:C30,"COMPRA") -> 5022.12
B14: 45505 | C14: COMPRA | D14: 10 | E14: 11.7 | F14: 0 | G14: =E14*D14 -> 117 | I14: Valor das Vendas | J14: =SUMIFS(E4:E30,C4:C30,"VENDA") -> 0
B15: 45505 | C15: COMPRA | D15: 21 | E15: 11.7 | F15: 0 | G15: =E15*D15 -> 245.7 | I15: Total de Taxas | J15: =SUM(F4:F30) -> 0
B16: 45595 | C16: COMPRA | D16: 47 | E16: 13 | F16: 0 | G16: =E16*D16 -> 611 | I16: Preço Médio | J16: =IF(J10<>0,((J13+J15)/J10),"") -> 13.286032
B17: 45628 | C17: COMPRA | D17: 12 | E17: 12.87 | F17: 0 | G17: =E17*D17 -> 154.44
B18: 45667 | C18: COMPRA | D18: 19 | E18: 11.4 | F18: 0 | G18: =E18*D18 -> 216.6
B19: 45758 | C19: COMPRA | D19: 10 | E19: 13.5 | F19: 0 | G19: =E19*D19 -> 135
B20: 45848 | C20: COMPRA | D20: 21 | E20: 13.26 | F20: 0 | G20: =E20*D20 -> 278.46
B21: 45922 | C21: COMPRA | D21: 21 | E21: 12.4 | F21: 0 | G21: =E21*D21 -> 260.4
B22: 45939 | C22: COMPRA | D22: 22 | E22: 11.79 | F22: 0 | G22: =E22*D22 -> 259.38
B23: 46000 | C23: COMPRA | D23: 17 | E23: 13.62 | F23: 0 | G23: =E23*D23 -> 231.54
B24: 46051 | C24: COMPRA | D24: 18 | E24: 14.71 | F24: 0 | G24: =E24*D24 -> 264.78
B25: 46087 | C25: COMPRA | D25: 22 | E25: 15.27 | F25: 0 | G25: =E25*D25 -> 335.94
B26: 46205 | C26: COMPRA | D26: 21 | E26: 16.4 | F26: 0 | G26: =E26*D26 -> 344.4

Sheet BTC
B2: ID | C2: BTCUSD | D2: Nome do Ativo | F2: Bitcoin
B3: Data | C3: Operação | D3: Qtde | E3: Valor unitário | F3: Taxas/Impostos | G3: Valor da operação | H3: Gráfico | K3: Dias graf
B4: 44627 | C4: Compra | D4: 0.00816 | E4: 195432 | F4: 0 | G4: =E4*D4 -> 1594.7251 | H4: =IFERROR(__xludf.DUMMYFUNCTION("IF(C2="""","""",SPARKLINE(GOOGLEFINANCE(C2,""price"",TODAY()-K4,TODAY())))"),"") | K4: 120
B5: 44630 | C5: Compra | D5: 0.00100938 | E5: 198140.1 | F5: 0 | G5: =E5*D5 -> 199.99865
B6: 44718 | C6: Venda | D6: 0.00916938 | E6: 150000 | F6: 9.71 | G6: 1378.06
B7: 44743 | C7: Compra | D7: 0.00239625 | E7: 103599.09 | F7: 0 | G7: =E7*D7 -> 248.24932
B8: 45945 | C8: Compra | D8: 0.00048698 | E8: 616041.73 | F8: 0 | G8: =E8*D8 -> 300
B9: 45945 | C9: Compra | D9: 0.00094831 | E9: 616041.73 | F9: 0 | G9: =E9*D9 -> 584.19853
B10: 46051 | C10: Compra | D10: 0.00187658 | E10: 443892.6 | F10: 0 | G10: =E10*D10 -> 832.99998 | I10: Qtde Comprada | J10: =SUMIFS(D4:D21,C4:C21,"COMPRA") -> 0.01680867
B11: 46087 | C11: Compra | D11: 0.00193117 | E11: 363352.88 | F11: 0 | G11: =E11*D11 -> 701.69618 | I11: Qtde Vendida | J11: =SUMIFS(D4:D21,C4:C21,"VENDA") -> 0.00916938
I12: Qtde em Carteira | J12: =J10-J11 -> 0.00763929
I13: Valor das Compras | J13: =SUMIFS(G7:G21,C7:C21,"COMPRA") -> 2667.144
I14: Valor das Vendas | J14: =SUMIFS(G4:G21,C4:C21,"VENDA") -> 1378.06
I15: Total de Taxas | J15: =SUM(F4:F21) -> 9.71
I16: Preço Médio | J16: =IF(J10<>0,((J13+J15)/J10),"") -> 159254.36

Sheet ETH
B2: ID | C2: ETHUSD | D2: Nome do Ativo | F2: Ethereum
B3: Data | C3: Operação | D3: Qtde | E3: Valor unitário | F3: Taxas/Impostos | G3: Valor da operação | H3: Gráfico | K3: Dias graf
B4: 44625 | C4: Compra | D4: 0.12712 | E4: 12872.99 | F4: 0 | G4: =E4*D4 -> 1636.4145 | H4: =IFERROR(__xludf.DUMMYFUNCTION("IF(C2="""","""",SPARKLINE(GOOGLEFINANCE(C2,""price"",TODAY()-K4,TODAY())))"),"") | K4: 60
B5: 44630 | C5: Compra | D5: =0.01519757 -> 0.01519757 | E5: 13159.98 | F5: =0.0001*E5 -> 1.315998 | G5: =E5*D5 -> 199.99972
B6: 44718 | C6: Venda | D6: 0.14231757 | E6: 9125.77 | F6: 8.98 | G6: 1274.89
B7: 44743 | C7: Compra | D7: =0.04348664-0.00055 -> 0.04293664 | E7: 5708.64 | F7: 1.71 | G7: =E7*D7 -> 245.10982
B8: 45945 | C8: Compra | D8: 0.0088633 | E8: 22565 | F8: 0 | G8: =E8*D8 -> 200.00036
B9: 46051 | C9: Compra | D9: 0.05626566 | E9: 14804.8 | F9: 0 | G9: =E9*D9 -> 833.00184
B10: 46087 | C10: COMPRA | D10: 0.06630408 | E10: 10528.76 | F10: 1.9 | G10: =E10*D10 -> 698.09975 | I10: Qtde Comprada | J10: =SUMIFS(D4:D21,C4:C21,"COMPRA") -> 0.31668725
I11: Qtde Vendida | J11: =SUMIFS(D4:D21,C4:C21,"VENDA") -> 0.14231757
I12: Qtde em Carteira | J12: =J10-J11 -> 0.17436968
I13: Valor das Compras | J13: =SUMIFS(G7:G21,C7:C21,"COMPRA") -> 1976.2118
I14: Valor das Vendas | J14: =SUMIFS(G4:G21,C4:C21,"VENDA") -> 1274.89
I15: Total de Taxas | J15: =SUM(F4:F21) -> 13.905998
I16: Preço Médio | J16: =IF(J10<>0,((J13+J15)/J10),"") -> 6284.174

Sheet PAXGOLD
B2: ID | C2: Pax Gold | D2: Nome do Ativo | F2: =IFERROR(__xludf.DUMMYFUNCTION("IF(C2="""","""",GOOGLEFINANCE(C2,""Name""))"),"#N/A") -> #N/A
B3: Data | C3: Operação | D3: Qtde | E3: Valor unitário | F3: Taxas/Impostos | G3: Valor da operação | H3: Gráfico | K3: Dias graf
B4: 45945 | C4: COMPRA | D4: 0.0214 | E4: 23031.76 | F4: =E4*0.0000214 -> 0.49287966 | G4: =E4*D4 -> 492.87966 | H4: =IFERROR(__xludf.DUMMYFUNCTION("IF(C2="""","""",SPARKLINE(GOOGLEFINANCE(C2,""price"",TODAY()-K4,TODAY())))"),"#N/A") -> #N/A | K4: 30
B5: 46051 | C5: COMPRA | D5: 0.02939708 | E5: 28224.768 | F5: 0 | G5: =E5*D5 -> 829.72576
B6: 46087 | C6: COMPRA | D6: 0.0217 | E6: 27188.64 | F6: 0 | G6: =E6*D6 -> 589.99349
I10: Qtde Comprada | J10: =SUMIFS(D4:D21,C4:C21,"COMPRA") -> 0.07249708
I11: Qtde Vendida | J11: =SUMIFS(D4:D21,C4:C21,"VENDA") -> 0
I12: Qtde em Carteira | J12: =J10-J11 -> 0.07249708
I13: Valor das Compras | J13: =SUMIFS(G4:G21,C4:C21,"COMPRA") -> 1912.5989
I14: Valor das Vendas | J14: =SUMIFS(E4:E21,C4:C21,"VENDA") -> 0
I15: Total de Taxas | J15: =SUM(F4:F21) -> 0.49287966
I16: Preço Médio | J16: =IF(J10<>0,((J13+J15)/J10),"") -> 26388.536

Sheet Tesouro Selic 2025
B2: ID | C2: TS2025 | D2: Nome da aplicação | E2: =IF(C2="","",VLOOKUP(C2,DB!A2:B1655,2,0)) -> Tesouro Selic 2025
B3: Data | C3: Operação | D3: Valor da operação | I3: Valor bruto Investido | J3: =SUM(D4:D21) -> -887.28
B4: 44630 | C4: COMPRA | D4: 14958.74 | I4: Valor Líquido atual | J4: 4195.74
B5: 44743 | C5: COMPRA | D5: 3900.28 | I5: Valorização R$ | J5: =J4-J3 -> 5083.02
B6: 44806 | C6: VENDA | D6: -800 | I6: Valorização % | J6: =IF(J4="","",(J5/J3)) -> -5.7287666
B7: 44841 | C7: COMPRA | D7: 3921.14
B8: 44997 | C8: COMPRA | D8: 3571.89
B9: 45168 | C9: VENDA | D9: -22243.59
B10: 45595 | C10: VENDA | D10: -4195.74

Sheet Tesouro IPCA+ 2024
B2: ID | C2: TI+2024 | D2: Nome da aplicação | E2: =IF(C2="","",VLOOKUP(C2,DB!A2:B1655,2,0)) -> Tesouro IPCA+ 2024
B3: Data | C3: Operação | D3: Valor da operação | I3: Valor bruto Investido | J3: 7467.31
B4: 44625 | C4: Compra | D4: 7467.31 | I4: Valor Líquido atual | J4: 0
B5: 45519 | C5: VENCIMENTO | D5: -10786.04 | I5: Valorização R$ | J5: =J4-J3 -> -7467.31
I6: Valorização % | J6: =IF(J4="","",(J5/J3)) -> -1

Sheet Tesouro Selic 2027
B2: ID | C2: TS2027 | D2: Nome da aplicação | E2: =IF(C2="","",VLOOKUP(C2,DB!A2:B1655,2,0)) -> Tesouro Selic 2027
B3: Data | C3: Operação | D3: Valor da operação | I3: Valor bruto Investido | J3: =SUM(D4:D21) -> 29884.98
B4: 45453 | C4: COMPRA | D4: 3874.4 | I4: Valor Líquido atual | J4: 38297.07
B5: 45505 | C5: COMPRA | D5: 2118.54 | I5: Valorização R$ | J5: =J4-J3 -> 8412.09
B6: 45551 | C6: COMPRA | D6: 1993.03 | I6: Valorização % | J6: =IF(J4="","",(J5/J3)) -> 0.2814822
B7: 45595 | C7: COMPRA | D7: 14911.43
B8: 45595 | C8: VENDA | D8: -2018.79
B9: 45628 | C9: COMPRA | D9: 2978.49
B10: 45667 | C10: COMPRA | D10: 6027.88

Sheet Tesouro Selic 2028
B2: ID | C2: TS2028 | D2: Nome da aplicação | E2: =IF(C2="","",VLOOKUP(C2,DB!A2:B1655,2,0)) -> Tesouro Selic 2028
B3: Data | C3: Operação | D3: Valor da operação | I3: Valor bruto Investido | J3: =SUM(D4:D21) -> 67343.78
B4: 45758 | C4: COMPRA | D4: 5395.72 | I4: Valor Líquido atual | J4: 75978.29
B5: 45848 | C5: COMPRA | D5: =7940.68+2872.16 -> 10812.84 | I5: Valorização R$ | J5: =J4-J3 -> 8634.51
B6: 45922 | C6: COMPRA | D6: 10433.91 | I6: Valorização % | J6: =IF(J4="","",(J5/J3)) -> 0.1282154
B7: 45939 | C7: COMPRA | D7: 5955.25
B8: 46000 | C8: COMPRA | D8: 11830.91
B9: 46000 | C9: COMPRA | D9: 5915.45
B10: 45686 | C10: COMPRA | D10: 16999.7

Sheet Tesouro Selic 2031
B2: ID | C2: TS2031 | D2: Nome da aplicação | E2: =IF(C2="","",VLOOKUP(C2,DB!A2:B1655,2,0)) -> Tesouro Selic 2031
B3: Data | C3: Operação | D3: Valor da operação | I3: Valor bruto Investido | J3: =SUM(D4:D12) -> 50546.38
B4: 46087 | C4: COMPRA | D4: 21032.61 | I4: Valor Líquido atual | J4: 52794.56
B5: 46087 | C5: COMPRA | D5: 19925.63 | I5: Valorização R$ | J5: =J4-J3 -> 2248.18
B6: 46128 | C6: VENDA | D6: -10112.08 | I6: Valorização % | J6: =IF(J4="","",(J5/J3)) -> 0.044477567
B7: 46206 | C7: COMPRA | D7: 24316.2
B8: 46244 | C8: VENDA | D8: -7784.08
B9: 46276 | C9: COMPRA | D9: 3168.1

Sheet Tesouro IPCA+ 2035
B2: ID | C2: TI+2035 | D2: Nome da aplicação | E2: =IF(C2="","",VLOOKUP(C2,DB!A2:B1655,2,0)) -> Tesouro IPCA+ 2035
B3: Data | C3: Operação | D3: Valor da operação | I3: Valor bruto Investido | J3: 0
B4: 44625 | C4: COMPRA | D4: 9964.64 | I4: Valor Líquido atual | J4: 0
B5: 44628 | C5: COMPRA | D5: 508.02 | I5: Valorização R$ | J5: =J4-J3 -> 0
B6: 44743 | C6: COMPRA | D6: 498.05 | I6: Valorização % | J6: 0
B7: 44841 | C7: COMPRA | D7: 509.35
B8: 45005 | C8: COMPRA | D8: 505.1
B9: 45246 | C9: COMPRA | D9: 2048.7
B10: 45300 | C10: COMPRA | D10: 2001.05
B11: 45341 | C11: COMPRA | D11: 12015.08
B12: 45356 | C12: COMPRA | D12: 4998.95
B13: 45370 | C13: VENDA | D13: -34453.76
B14: 45421 | C14: COMPRA | D14: 1997.64
B15: 45453 | C15: COMPRA | D15: 3988.3
B16: 45523 | C16: COMPRA | D16: 10980.12
B17: 45551 | C17: COMPRA | D17: 2096.23
B18: 45595 | C18: COMPRA | D18: 4993.75
... B21: 46083 | C21: VENDA | D21: -28414.86

Sheet Tesouro Educa+ 2043
B2: ID | C2: TE+2043 | D2: Nome da aplicação | E2: =IF(C2="","",VLOOKUP(C2,DB!A2:B1655,2,0)) -> Tesouro Educa+ 2043
B3: Data | C3: Operação | D3: Valor da operação | I3: Valor bruto Investido | J3: =SUM(D4:D21) -> 3794.23
B4: 46206 | C4: COMPRA | D4: 2509.26 | I4: Valor Líquido atual | J4: 3786.53
B5: 46238 | C5: COMPRA | D5: 647.9 | I5: Valorização R$ | J5: =J4-J3 -> -7.7
B6: 46269 | C6: COMPRA | D6: 637.07 | I6: Valorização % | J6: =IF(J4="","",(J5/J3)) -> -0.0020293973

Sheet Tesouro Renda+ 2055
B2: ID | C2: TR+2055 | D2: Nome da aplicação | E2: =IF(C2="","",VLOOKUP(C2,DB!A2:B1655,2,0)) -> Tesouro Renda+ 2055
B3: Data | C3: Operação | D3: Valor da operação | I3: Valor bruto Investido | J3: =SUM(D4:D21) -> 6449.86
B4: 46206 | C4: COMPRA | D4: 2149.81 | I4: Valor Líquido atual | J4: 6154.86
B5: 46238 | C5: COMPRA | D5: 2150.73 | I5: Valorização R$ | J5: =J4-J3 -> -295
B6: 46269 | C6: COMPRA | D6: 2149.32 | I6: Valorização % | J6: =IF(J4="","",(J5/J3)) -> -0.045737427

Sheet Privilege DI
B2: ID | C2: FUNDDI | D2: Nome da aplicação | E2: =IF(C2="","",VLOOKUP(C2,DB!A2:B1655,2,0)) -> Fundo Privelege DI
B3: Data | C3: Operação | D3: Valor da operação | I3: Valor bruto Investido | J3: 0
B4: 44628 | C4: COMPRA | D4: 1000 | I4: Valor Líquido atual | J4: 0
B5: 44652 | C5: COMPRA | D5: 500 | I5: Valorização R$ | J5: 0
B6: 44743 | C6: COMPRA | D6: 500 | I6: Valorização % | J6: 0
B7: 44866 | C7: VENDA | D7: -700
B8: 44992 | C8: VENDA | D8: -1332.87
B9: 45028 | C9: COMPRA | D9: 1000
B10: 45058 | C10: COMPRA | D10: 2600
B11: 45170 | C11: VENDA | D11: -3645.01

Sheet FUNDITPETR
B2: ID | C2: FUNDITPETR | D2: Nome da aplicação | E2: =IF(C2="","",VLOOKUP(C2,DB!A2:B1655,2,0)) -> Fundo Index Petrobras
B3: Data | C3: Operação | D3: Valor da operação | I3: Valor bruto Investido | J3: 0
B4: 44628 | C4: COMPRA | D4: 500 | I4: Valor Líquido atual | J4: 0
B5: 44652 | C5: COMPRA | D5: 250 | I5: Valorização R$ | J5: =J4-J3 -> 0
B6: 44992 | C6: VENDA | D6: -899.47 | I6: Valorização % | J6: 0

Sheet FUNDITSP500
B2: ID | C2: FUNDITSP500 | D2: Nome da aplicação | E2: =IF(C2="","",VLOOKUP(C2,DB!A2:B1655,2,0)) -> Fundo Index SP500
B3: Data | C3: Operação | D3: Valor da operação | I3: Valor bruto Investido | J3: =SUM(D4:D21) -> -32.8
B4: 44628 | C4: COMPRA | D4: 500 | I4: Valor Líquido atual | J4: 0
B5: 44652 | C5: COMPRA | D5: 250 | I5: Valorização R$ | J5: 0
B6: 45170 | C6: VENDA | D6: -782.8 | I6: Valorização % | J6: =IF(J4="","",(J5/J3)) -> 0

Sheet POUP
B2: ID | C2: POUP | D2: Nome da aplicação | E2: =IF(C2="","",VLOOKUP(C2,DB!A2:B1655,2,0)) -> Poupança Itaú
B3: Data | C3: Operação | D3: Valor da operação | I3: Valor bruto Investido | J3: 0
B4: 44628 | C4: COMPRA | D4: 40496.7 | I4: Valor Líquido atual | J4: 0
B5: 44630 | C5: VENDA | D5: -15400 | I5: Valorização R$ | J5: =J4-J3 -> 0
B6: 44651 | C6: COMPRA | D6: 2000.4 | I6: Valorização % | J6: 0
B7: 44681 | C7: VENDA | D7: -12769
B8: 44694 | C8: VENDA | D8: -946
B9: 44712 | C9: VENDA | D9: -8866
B10: 44716 | C10: VENDA | D10: -4515.55
B11: 44743 | C11: COMPRA | D11: 2000
B12: 44748 | C12: VENDA | D12: 1500
B13: 44782 | C13: VENDA | D13: -500

Sheet Tabela dinâmica - RV
K1: Pct% lucro
K2: =(I2-J2)/J2 -> 0.20734463
K3: =(I3-J3)/J3 -> 0.25083379
K4: =(I4-J4)/J4 -> -0.032032051
K5: =(I5-J5)/J5 -> 0.31414407
K6: =(I6-J6)/J6 -> #DIV/0!

Sheet Tabela dinâmica - RF
K1: Pct% lucro
K2: =(I2-J2)/J2 -> 0.12018841
K3: =(I3-J3)/J3 -> #DIV/0!
K4: =(I4-J4)/J4 -> #DIV/0!

Sheet DB
A1: CODIGO | B1: NOME | C1: CNPJ | D1: SETOR ECONÔMICO | E1: SUBSETOR | F1: SEGMENTO / ADM / PAÍS | G1: TIPO
A2: CSAN3 | B2: =IFERROR(__xludf.DUMMYFUNCTION("GOOGLEFINANCE(A2,""Name"")"),"Cosan SA") -> Cosan SA | C2: 50.746.577/0001-15 | D2: Petróleo, Gás e Biocombustíveis | E2: Petróleo, Gás e Biocombustíveis | F2: Exploração, Refino e Distribuição | G2: Ação
A3: DMMO3 | B3: =IFERROR(__xludf.DUMMYFUNCTION("GOOGLEFINANCE(A3,""Name"")"),"#N/A") -> #N/A | C3: 08.926.302/0001-05 | D3: Petróleo, Gás e Biocombustíveis | E3: Petróleo, Gás e Biocombustíveis | F3: Exploração, Refino e Distribuição | G3: Ação
A4: DMMO11 | B4: =IFERROR(__xludf.DUMMYFUNCTION("GOOGLEFINANCE(A4,""Name"")"),"#N/A") -> #N/A | C4: 08.926.302/0001-05 | D4: Petróleo, Gás e Biocombustíveis | E4: Petróleo, Gás e Biocombustíveis | F4: Exploração, Refino e Distribuição | G4: Ação
A5: ENAT3 | B5: =IFERROR(__xludf.DUMMYFUNCTION("GOOGLEFINANCE(A5,""Name"")"),"#N/A") -> #N/A | C5: 11.669.021/0001-10 | D5: Petróleo, Gás e Biocombustíveis | E5: Petróleo, Gás e Biocombustíveis | F5: Exploração, Refino e Distribuição | G5: Ação
A6: RPMG3 | B6: =IFERROR(__xludf.DUMMYFUNCTION("GOOGLEFINANCE(A6,""Name"")"),"Refinaria de Petroleos d Mng S em Rcp Jd") -> Refinaria de Petroleos d Mng S em Rcp Jd | C6: 33.412.081/0001-96 | D6: Petróleo, Gás e Biocombustíveis | E6: Petróleo, Gás e Biocombustíveis | F6: Exploração, Refino e Distribuição | G6: Ação
A7: PETR3 | B7: =IFERROR(__xludf.DUMMYFUNCTION("GOOGLEFINANCE(A7,""Name"")"),"Petrobras Brasileiro Cedear") -> Petrobras Brasileiro Cedear | C7: 33.000.167/0001-01 | D7: Petróleo, Gás e Biocombustíveis | E7: Petróleo, Gás e Biocombustíveis | F7: Exploração, Refino e Distribuição | G7: Ação
A8: PETR4 | B8: =IFERROR(__xludf.DUMMYFUNCTION("GOOGLEFINANCE(A8,""Name"")"),"Petroleo Brasileiro SA Petrobras Preference Shares") -> Petroleo Brasileiro SA Petrobras Preference Shares | C8: 33.000.167/0001-01 | D8: Petróleo, Gás e Biocombustíveis | E8: Petróleo, Gás e Biocombustíveis | F8: Exploração, Refino e Distribuição | G8: Ação
A9: BRDT3 | B9: =IFERROR(__xludf.DUMMYFUNCTION("GOOGLEFINANCE(A9,""Name"")"),"#N/A") -> #N/A | C9: 34.274.233/0001-02 | D9: Petróleo, Gás e Biocombustíveis | E9: Petróleo, Gás e Biocombustíveis | F9: Exploração, Refino e Distribuição | G9: Ação
A10: VBBR3 | B10: =IFERROR(__xludf.DUMMYFUNCTION("GOOGLEFINANCE(A10,""Name"")"),"Vibra Energia SA") -> Vibra Energia SA | C10: 34.274.233/0001-02 | D10: Petróleo, Gás e Biocombustíveis | E10: Petróleo, Gás e Biocombustíveis | F10: Exploração, Refino e Distribuição | G10: Ação
A11: PRIO3 | B11: =IFERROR(__xludf.DUMMYFUNCTION("GOOGLEFINANCE(A11,""Name"")"),"Prio Cedar") -> Prio Cedar | C11: 10.629.105/0001-68 | D11: Petróleo, Gás e Biocombustíveis | E11: Petróleo, Gás e Biocombustíveis | F11: Exploração, Refino e Distribuição | G11: Ação
A12: UGPA3 | B12: =IFERROR(__xludf.DUMMYFUNCTION("GOOGLEFINANCE(A12,""Name"")"),"Ultrapar Participacoes SA") -> Ultrapar Participacoes SA | C12: 33.256.439/0001-39 | D12: Petróleo, Gás e Biocombustíveis | E12: Petróleo, Gás e Biocombustíveis | F12: Exploração, Refino e Distribuição | G12: Ação
A13: LUPA3 | B13: =IFERROR(__xludf.DUMMYFUNCTION("GOOGLEFINANCE(A13,""Name"")"),"Lupatech SA") -> Lupatech SA | C13: 89.463.822/0001-12 | D13: Petróleo, Gás e Biocombustíveis | E13: Petróleo, Gás e Biocombustíveis | F13: Equipamentos e Serviços | G13: Ação
A14: OSXB3 | B14: =IFERROR(__xludf.DUMMYFUNCTION("GOOGLEFINANCE(A14,""Name"")"),"OSX BRASIL SA") -> OSX BRASIL SA | C14: 09.112.685/0001-32 | D14: Petróleo, Gás e Biocombustíveis | E14: Petróleo, Gás e Biocombustíveis | F14: Equipamentos e Serviços | G14: Ação
A15: BRAP3 | B15: =IFERROR(__xludf.DUMMYFUNCTION("GOOGLEFINANCE(A15,""Name"")"),"Bradespar SA") -> Bradespar SA | C15: 03.847.461/0001-92 | D15: Materiais Básicos | E15: Mineração | F15: Minerais Metálicos | G15: Ação
A16: BRAP4 | B16: =IFERROR(__xludf.DUMMYFUNCTION("GOOGLEFINANCE(A16,""Name"")"),"Bradespar SA Preference Shares") -> Bradespar SA Preference Shares | C16: 03.847.461/0001-92 | D16: Materiais Básicos | E16: Mineração | F16: Minerais Metálicos | G16: Ação
A17: LTEL3B | B17: =IFERROR(__xludf.DUMMYFUNCTION("GOOGLEFINANCE(A17,""Name"")"),"Litel Participacoes S/A") -> Litel Participacoes S/A | C17: 00.743.065/0001-27 | D17: Materiais Básicos | E17: Mineração | F17: Minerais Metálicos | G17: Ação
A18: LTLA3B | B18: =IFERROR(__xludf.DUMMYFUNCTION("GOOGLEFINANCE(A18,""Name"")"),"LITELA ON MB") -> LITELA ON MB | C18: 05.495.546/0001-84 | D18: Materiais Básicos | E18: Mineração | F18: Minerais Metálicos | G18: Ação
A19: MMXM3 | B19: =IFERROR(__xludf.DUMMYFUNCTION("GOOGLEFINANCE(A19,""Name"")"),"#N/A") -> #N/A | C19: 02.762.115/0001-49 | D19: Materiais Básicos | E19: Mineração | F19: Minerais Metálicos | G19: Ação
A20: VALE3 | B20: =IFERROR(__xludf.DUMMYFUNCTION("GOOGLEFINANCE(A20,""Name"")"),"Vale Cedear") -> Vale Cedear | C20: 33.592.510/0001-54 | D20: Materiais Básicos | E20: Mineração | F20: Minerais Metálicos | G20: Ação
A21: FESA3 | B21: =IFERROR(__xludf.DUMMYFUNCTION("GOOGLEFINANCE(A21,""Name"")"),"Companhia de Ferro Ligas da Bah Frbs") -> Companhia de Ferro Ligas da Bah Frbs | C21: 15.141.799/0001-03 | D21: Materiais Básicos | E21: Siderurgia e Metalurgia | F21: Siderurgia | G21: Ação
A22: FESA4 | B22: =IFERROR(__xludf.DUMMYFUNCTION("GOOGLEFINANCE(A22,""Name"")"),"Companhia de Ferro Ligas da Bah Frbs Preference Shares") -> Companhia de Ferro Ligas da Bah Frbs Preference Shares | C22: 15.141.799/0001-03 | D22: Materiais Básicos | E22: Siderurgia e Metalurgia | F22: Siderurgia | G22: Ação
A23: GGBR3 | B23: =IFERROR(__xludf.DUMMYFUNCTION("GOOGLEFINANCE(A23,""Name"")"),"Gerdau SA") -> Gerdau SA | C23: 33.611.500/0001-19 | D23: Materiais Básicos | E23: Siderurgia e Metalurgia | F23: Siderurgia | G23: Ação
A24: GGBR4 | B24: =IFERROR(__xludf.DUMMYFUNCTION("GOOGLEFINANCE(A24,""Name"")"),"Gerdau SA Preference Shares") -> Gerdau SA Preference Shares | C24: 33.611.500/0001-19 | D24: Materiais Básicos | E24: Siderurgia e Metalurgia | F24: Siderurgia | G24: Ação
A25: GOAU3 | B25: =IFERROR(__xludf.DUMMYFUNCTION("GOOGLEFINANCE(A25,""Name"")"),"Metalurgica Gerdau SA") -> Metalurgica Gerdau SA | C25: 92.690.783/0001-09 | D25: Materiais Básicos | E25: Siderurgia e Metalurgia | F25: Siderurgia | G25: Ação
A26: GOAU4 | B26: =IFERROR(__xludf.DUMMYFUNCTION("GOOGLEFINANCE(A26,""Name"")"),"Metalurgica Gerdau SA Preference Shares") -> Metalurgica Gerdau SA Preference Shares | C26: 92.690.783/0001-09 | D26: Materiais Básicos | E26: Siderurgia e Metalurgia | F26: Siderurgia | G26: Ação
A27: CSNA3 | B27: =IFERROR(__xludf.DUMMYFUNCTION("GOOGLEFINANCE(A27,""Name"")"),"Cia Siderurgica Nacional Cedear") -> Cia Siderurgica Nacional Cedear | C27: 33.042.730/0001-04 | D27: Materiais Básicos | E27: Siderurgia e Metalurgia | F27: Siderurgia | G27: Ação
A28: USIM3 | B28: =IFERROR(__xludf.DUMMYFUNCTION("GOOGLEFINANCE(A28,""Name"")"),"Usinas Siderurgicas de Mins Grs SA USMNS") -> Usinas Siderurgicas de Mins Grs SA USMNS | C28: 60.894.730/0001-05 | D28: Materiais Básicos | E28: Siderurgia e Metalurgia | F28: Siderurgia | G28: Ação
A29: USIM5 | B29: =IFERROR(__xludf.DUMMYFUNCTION("GOOGLEFINANCE(A29,""Name"")"),"Usinas Siderurgicas de Mins Grs SA USMNS Preference Shares Class A") -> Usinas Siderurgicas de Mins Grs SA USMNS Preference Shares Class A | C29: 60.894.730/0001-05 | D29: Materiais Básicos | E29: Siderurgia e Metalurgia | F29: Siderurgia | G29: Ação
A30: USIM6 | B30: =IFERROR(__xludf.DUMMYFUNCTION("GOOGLEFINANCE(A30,""Name"")"),"Usinas Siderurgicas de Mins Grs SA USMNS Preference Shares Class B") -> Usinas Siderurgicas de Mins Grs SA USMNS Preference Shares Class B | C30: 60.894.730/0001-05 | D30: Materiais Básicos | E30: Siderurgia e Metalurgia | F30: Siderurgia | G30: Ação
A31: MGEL3 | B31: =IFERROR(__xludf.DUMMYFUNCTION("GOOGLEFINANCE(A31,""Name"")"),"Mangels Industrial SA") -> Mangels Industrial SA | C31: 61.065.298/0001-02 | D31: Materiais Básicos | E31: Siderurgia e Metalurgia | F31: Artefatos de Ferro e Aço | G31: Ação
A32: MGEL4 | B32: =IFERROR(__xludf.DUMMYFUNCTION("GOOGLEFINANCE(A32,""Name"")"),"Mangels Industrial SA Preference Shares") -> Mangels Industrial SA Preference Shares | C32: 61.065.298/0001-02 | D32: Materiais Básicos | E32: Siderurgia e Metalurgia | F32: Artefatos de Ferro e Aço | G32: Ação
A33: PATI3 | B33: =IFERROR(__xludf.DUMMYFUNCTION("GOOGLEFINANCE(A33,""Name"")"),"Panatlantica SA") -> Panatlantica SA | C33: 92.693.019/0001-89 | D33: Materiais Básicos | E33: Siderurgia e Metalurgia | F33: Artefatos de Ferro e Aço | G33: Ação
A34: PATI4 | B34: =IFERROR(__xludf.DUMMYFUNCTION("GOOGLEFINANCE(A34,""Name"")"),"Panatlantica SA Preference Shares") -> Panatlantica SA Preference Shares | C34: 92.693.019/0001-89 | D34: Materiais Básicos | E34: Siderurgia e Metalurgia | F34: Artefatos de Ferro e Aço | G34: Ação
A35: TKNO3 | B35: =IFERROR(__xludf.DUMMYFUNCTION("GOOGLEFINANCE(A35,""Name"")"),"#N/A") -> #N/A | C35: 33.467.572/0001-34 | D35: Materiais Básicos | E35: Siderurgia e Metalurgia | F35: Artefatos de Ferro e Aço | G35: Ação
A36: TKNO4 | B36: =IFERROR(__xludf.DUMMYFUNCTION("GOOGLEFINANCE(A36,""Name"")"),"#N/A") -> #N/A | C36: 33.467.572/0001-34 | D36: Materiais Básicos | E36: Siderurgia e Metalurgia | F36: Artefatos de Ferro e Aço | G36: Ação
A37: PMAM3 | B37: =IFERROR(__xludf.DUMMYFUNCTION("GOOGLEFINANCE(A37,""Name"")"),"Paranapanema SA Em Recuperacao Judicial") -> Paranapanema SA Em Recuperacao Judicial | C37: 60.398.369/0004-79 | D37: Materiais Básicos | E37: Siderurgia e Metalurgia | F37: Artefatos de Cobre | G37: Ação
A38: BRKM3 | B38: =IFERROR(__xludf.DUMMYFUNCTION("GOOGLEFINANCE(A38,""Name"")"),"Braskem SA") -> Braskem SA | C38: 42.150.391/0001-70 | D38: Materiais Básicos | E38: Químicos | F38: Petroquímicos | G38: Ação
A39: BRKM5 | B39: =IFERROR(__xludf.DUMMYFUNCTION("GOOGLEFINANCE(A39,""Name"")"),"Braskem SA Preference Shares Class A") -> Braskem SA Preference Shares Class A | C39: 42.150.391/0001-70 | D39: Materiais Básicos | E39: Químicos | F39: Petroquímicos | G39: Ação
A40: BRKM6 | B40: =IFERROR(__xludf.DUMMYFUNCTION("GOOGLEFINANCE(A40,""Name"")"),"Braskem SA Preference Shares Class B") -> Braskem SA Preference Shares Class B | C40: 42.150.391/0001-70 | D40: Materiais Básicos | E40: Químicos | F40: Petroquímicos | G40: Ação
A41: EKTR3 | B41: =IFERROR(__xludf.DUMMYFUNCTION("GOOGLEFINANCE(A41,""Name"")"),"Elektro Redes SA") -> Elektro Redes SA | C41: 02.328.280/0001-97 | D41: Materiais Básicos | E41: Químicos | F41: Petroquímicos | G41: Ação
A42: EKTR4 | B42: =IFERROR(__xludf.DUMMYFUNCTION("GOOGLEFINANCE(A42,""Name"")"),"Elektro Redes SA Preference Shares") -> Elektro Redes SA Preference Shares | C42: 02.328.280/0001-97 | D42: Materiais Básicos | E42: Químicos | F42: Petroquímicos | G42: Ação
A43: DEXP3 | B43: =IFERROR(__xludf.DUMMYFUNCTION("GOOGLEFINANCE(A43,""Name"")"),"Dexxos Participacoes SA") -> Dexxos Participacoes SA | C43: 02.193.750/0001-52 | D43: Materiais Básicos | E43: Químicos | F43: Petroquímicos | G43: Ação
A44: DEXP4 | B44: =IFERROR(__xludf.DUMMYFUNCTION("GOOGLEFINANCE(A44,""Name"")"),"Dexxos Participacoes SA Preference Shares") -> Dexxos Participacoes SA Preference Shares | C44: 02.193.750/0001-52 | D44: Materiais Básicos | E44: Químicos | F44: Petroquímicos | G44: Ação
A45: FHER3 | B45: =IFERROR(__xludf.DUMMYFUNCTION("GOOGLEFINANCE(A45,""Name"")"),"Fertilizantes Heringer SA") -> Fertilizantes Heringer SA | C45: 22.266.175/0001-88 | D45: Materiais Básicos | E45: Químicos | F45: Fertilizantes e Defensivos | G45: Ação
A46: NUTR3 | B46: =IFERROR(__xludf.DUMMYFUNCTION("GOOGLEFINANCE(A46,""Name"")"),"Nutriplant Industria e Comercio S/A") -> Nutriplant Industria e Comercio S/A | C46: 51.128.999/0001-90 | D46: Materiais Básicos | E46: Químicos | F46: Fertilizantes e Defensivos | G46: Ação
A47: CRPG3 | B47: =IFERROR(__xludf.DUMMYFUNCTION("GOOGLEFINANCE(A47,""Name"")"),"Tronox Pigmentos do Brasil SA") -> Tronox Pigmentos do Brasil SA | C47: 15.115.504/0001-24 | D47: Materiais Básicos | E47: Químicos | F47: Químicos Diversos | G47: Ação
A48: CRPG5 | B48: =IFERROR(__xludf.DUMMYFUNCTION("GOOGLEFINANCE(A48,""Name"")"),"Cristal Pigmentos do Brasil Pref Shs A") -> Cristal Pigmentos do Brasil Pref Shs A | C48: 15.115.504/0001-24 | D48: Materiais Básicos | E48: Químicos | F48: Químicos Diversos | G48: Ação
A49: CRPG6 | B49: =IFERROR(__xludf.DUMMYFUNCTION("GOOGLEFINANCE(A49,""Name"")"),"Cristal Pigmentos do Brasil Pref Shs B") -> Cristal Pigmentos do Brasil Pref Shs B | C49: 15.115.504/0001-24 | D49: Materiais Básicos | E49: Químicos | F49: Químicos Diversos | G49: Ação
A50: UNIP3 | B50: =IFERROR(__xludf.DUMMYFUNCTION("GOOGLEFINANCE(A50,""Name"")"),"Unipar Carbocloro SA") -> Unipar Carbocloro SA | C50: 33.958.695/0001-78 | D50: Materiais Básicos | E50: Químicos | F50: Químicos Diversos | G50: Ação
A51: UNIP5 | B51: =IFERROR(__xludf.DUMMYFUNCTION("GOOGLEFINANCE(A51,""Name"")"),"Unipar Carbocloro SA Preference Shares Class A") -> Unipar Carbocloro SA Preference Shares Class A | C51: 33.958.695/0001-78 | D51: Materiais Básicos | E51: Químicos | F51: Químicos Diversos | G51: Ação
A52: UNIP6 | B52: =IFERROR(__xludf.DUMMYFUNCTION("GOOGLEFINANCE(A52,""Name"")"),"Unipar Carbocloro SA Preference Shares Class B") -> Unipar Carbocloro SA Preference Shares Class B | C52: 33.958.695/0001-78 | D52: Materiais Básicos | E52: Químicos | F52: Químicos Diversos | G52: Ação
A53: DXCO3 | B53: =IFERROR(__xludf.DUMMYFUNCTION("GOOGLEFINANCE(A53,""Name"")"),"Dexco SA") -> Dexco SA | C53: 97.837.181/0001-47 | D53: Materiais Básicos | E53: Madeira e Papel | F53: Madeira | G53: Ação
A54: EUCA3 | B54: =IFERROR(__xludf.DUMMYFUNCTION("GOOGLEFINANCE(A54,""Name"")"),"Eucatex SA Industria e Comercio") -> Eucatex SA Industria e Comercio | C54: 56.643.018/0001-66 | D54: Materiais Básicos | E54: Madeira e Papel | F54: Madeira | G54: Ação
A55: EUCA4 | B55: =IFERROR(__xludf.DUMMYFUNCTION("GOOGLEFINANCE(A55,""Name"")"),"Eucatex SA Industria e Comercio Preference Shares") -> Eucatex SA Industria e Comercio Preference Shares | C55: 56.643.018/0001-66 | D55: Materiais Básicos | E55: Madeira e Papel | F55: Madeira | G55: Ação
A56: RANI3 | B56: =IFERROR(__xludf.DUMMYFUNCTION("GOOGLEFINANCE(A56,""Name"")"),"Irani Papel e Embalagem SA") -> Irani Papel e Embalagem SA | C56: 92.791.243/0001-03 | D56: Materiais Básicos | E56: Madeira e Papel | F56: Papel e Celulose | G56: Ação
A57: RANI4 | B57: =IFERROR(__xludf.DUMMYFUNCTION("GOOGLEFINANCE(A57,""Name"")"),"#N/A") -> #N/A | C57: 92.791.243/0001-03 | D57: Materiais Básicos | E57: Madeira e Papel | F57: Papel e Celulose | G57: Ação
A58: KLBN3 | B58: =IFERROR(__xludf.DUMMYFUNCTION("GOOGLEFINANCE(A58,""Name"")"),"Klabin SA") -> Klabin SA | C58: 89.637.490/0001-45 | D58: Materiais Básicos | E58: Madeira e Papel | F58: Papel e Celulose | G58: Ação
A59: KLBN4 | B59: =IFERROR(__xludf.DUMMYFUNCTION("GOOGLEFINANCE(A59,""Name"")"),"Klabin SA Preference Shares") -> Klabin SA Preference Shares | C59: 89.637.490/0001-45 | D59: Materiais Básicos | E59: Madeira e Papel | F59: Papel e Celulose | G59: Ação
A60: KLBN11 | B60: =IFERROR(__xludf.DUMMYFUNCTION("GOOGLEFINANCE(A60,""Name"")"),"Klabin SA Unit") -> Klabin SA Unit | C60: 89.637.490/0001-45 | D60: Materiais Básicos | E60: Madeira e Papel | F60: Papel e Celulose | G60: Ação
A61: MSPA3 | B61: =IFERROR(__xludf.DUMMYFUNCTION("GOOGLEFINANCE(A61,""Name"")"),"Companhia Melhoramentos de Sao Paulo") -> Companhia Melhoramentos de Sao Paulo | C61: 60.730.348/0001-66 | D61: Materiais Básicos | E61: Madeira e Papel | F61: Papel e Celulose | G61: Ação
A62: MSPA3 | B62: =IFERROR(__xludf.DUMMYFUNCTION("GOOGLEFINANCE(A62,""Name"")"),"Companhia Melhoramentos de Sao Paulo") -> Companhia Melhoramentos de Sao Paulo | C62: 60.730.348/0001-66 | D62: Materiais Básicos | E62: Madeira e Papel | F62: Papel e Celulose | G62: Ação
A63: NEMO3 | B63: =IFERROR(__xludf.DUMMYFUNCTION("GOOGLEFINANCE(A63,""Name"")"),"Suzano Holding SA") -> Suzano Holding SA | C63: 60.651.809/0001-05 | D63: Materiais Básicos | E63: Madeira e Papel | F63: Papel e Celulose | G63: Ação
A64: NEMO5 | B64: =IFERROR(__xludf.DUMMYFUNCTION("GOOGLEFINANCE(A64,""Name"")"),"#N/A") -> #N/A | C64: 60.651.809/0001-05 | D64: Materiais Básicos | E64: Madeira e Papel | F64: Papel e Celulose | G64: Ação
A65: NEMO6 | B65: =IFERROR(__xludf.DUMMYFUNCTION("GOOGLEFINANCE(A65,""Name"")"),"#N/A") -> #N/A | C65: 60.651.809/0001-05 | D65: Materiais Básicos | E65: Madeira e Papel | F65: Papel e Celulose | G65: Ação
A66: SUZB3 | B66: =IFERROR(__xludf.DUMMYFUNCTION("GOOGLEFINANCE(A66,""Name"")"),"Suzano Cedear") -> Suzano Cedear | C66: 16.404.287/0001-55 | D66: Materiais Básicos | E66: Madeira e Papel | F66: Papel e Celulose | G66: Ação
A67: MTIG3 | B67: =IFERROR(__xludf.DUMMYFUNCTION("GOOGLEFINANCE(A67,""Name"")"),"#N/A") -> #N/A | C67: 80.227.184/0001-66 | D67: Materiais Básicos | E67: Embalagens | F67: Embalagens | G67: Ação
A68: MTIG4 | B68: =IFERROR(__xludf.DUMMYFUNCTION("GOOGLEFINANCE(A68,""Name"")"),"#N/A") -> #N/A | C68: 80.227.184/0001-66 | D68: Materiais Básicos | E68: Embalagens | F68: Embalagens | G68: Ação
A69: SNSY3 | B69: =IFERROR(__xludf.DUMMYFUNCTION("GOOGLEFINANCE(A69,""Name"")"),"Sansuy S/A Industria de Plasticos") -> Sansuy S/A Industria de Plasticos | C69: 14.807.945/0001-24 | D69: Materiais Básicos | E69: Materiais Diversos | F69: Materiais Diversos | G69: Ação
A70: SNSY5 | B70: =IFERROR(__xludf.DUMMYFUNCTION("GOOGLEFINANCE(A70,""Name"")"),"Sansuy S/A Industria de Plasticos Preference Shares Class A") -> Sansuy S/A Industria de Plasticos Preference Shares Class A | C70: 14.807.945/0001-24 | D70: Materiais Básicos | E70: Materiais Diversos | F70: Materiais Diversos | G70: Ação
A71: SNSY6 | B71: =IFERROR(__xludf.DUMMYFUNCTION("GOOGLEFINANCE(A71,""Name"")"),"Sansuy S/A Industria de Plasticos Preference Shares Class B") -> Sansuy S/A Industria de Plasticos Preference Shares Class B | C71: 14.807.945/0001-24 | D71: Materiais Básicos | E71: Materiais Diversos | F71: Materiais Diversos | G71: Ação
A72: ETER3 | B72: =IFERROR(__xludf.DUMMYFUNCTION("GOOGLEFINANCE(A72,""Name"")"),"Eternit SA em Recuperacao Judicial") -> Eternit SA em Recuperacao Judicial | C72: 61.092.037/0001-81 | D72: Bens Industriais | E72: Construção e Engenharia | F72: Produtos para Construção | G72: Ação
A73: HAGA3 | B73: =IFERROR(__xludf.DUMMYFUNCTION("GOOGLEFINANCE(A73,""Name"")"),"Haga SA Industria e Comercio") -> Haga SA Industria e Comercio | C73: 30.540.991/0001-66 | D73: Bens Industriais | E73: Construção e Engenharia | F73: Produtos para Construção | G73: Ação
A74: HAGA4 | B74: =IFERROR(__xludf.DUMMYFUNCTION("GOOGLEFINANCE(A74,""Name"")"),"Haga SA Industria e Comercio Preference Shares") -> Haga SA Industria e Comercio Preference Shares | C74: 30.540.991/0001-66 | D74: Bens Industriais | E74: Construção e Engenharia | F74: Produtos para Construção | G74: Ação
A75: PTBL3 | B75: =IFERROR(__xludf.DUMMYFUNCTION("GOOGLEFINANCE(A75,""Name"")"),"PBG SA") -> PBG SA | C75: 83.475.913/0001-91 | D75: Bens Industriais | E75: Construção e Engenharia | F75: Produtos para Construção | G75: Ação
A76: AZEV3 | B76: =IFERROR(__xludf.DUMMYFUNCTION("GOOGLEFINANCE(A76,""Name"")"),"Azevedo & Travassos SA") -> Azevedo & Travassos SA | C76: 61.351.532/0001-68 | D76: Bens Industriais | E76: Construção e Engenharia | F76: Construção Pesada | G76: Ação
A77: AZEV4 | B77: =IFERROR(__xludf.DUMMYFUNCTION("GOOGLEFINANCE(A77,""Name"")"),"Azevedo & Travassos SA Preference Shares") -> Azevedo & Travassos SA Preference Shares | C77: 61.351.532/0001-68 | D77: Bens Industriais | E77: Construção e Engenharia | F77: Construção Pesada | G77: Ação
A78: SOND3 | B78: =IFERROR(__xludf.DUMMYFUNCTION("GOOGLEFINANCE(A78,""Name"")"),"Sondotecnica Engenharia de Solos SA") -> Sondotecnica Engenharia de Solos SA | C78: 33.386.210/0001-19 | D78: Bens Industriais | E78: Construção e Engenharia | F78: Engenharia Consultiva | G78: Ação
A79: SOND5 | B79: =IFERROR(__xludf.DUMMYFUNCTION("GOOGLEFINANCE(A79,""Name"")"),"Sondotecnica Engenharia de Solos SA Preference Shares Class A") -> Sondotecnica Engenharia de Solos SA Preference Shares Class A | C79: 33.386.210/0001-19 | D79: Bens Industriais | E79: Construção e Engenharia | F79: Engenharia Consultiva | G79: Ação
A80: SOND6 | B80: =IFERROR(__xludf.DUMMYFUNCTION("GOOGLEFINANCE(A80,""Name"")"),"Sondotecnica Engenharia de Solos SA Preference Shares Class B") -> Sondotecnica Engenharia de Solos SA Preference Shares Class B | C80: 33.386.210/0001-19 | D80: Bens Industriais | E80: Construção e Engenharia | F80: Engenharia Consultiva | G80: Ação
A81: TCNO3 | B81: =IFERROR(__xludf.DUMMYFUNCTION("GOOGLEFINANCE(A81,""Name"")"),"#N/A") -> #N/A | C81: 33.111.246/0001-90 | D81: Bens Industriais | E81: Construção e Engenharia | F81: Engenharia Consultiva | G81: Ação
A82: TCNO4 | B82: =IFERROR(__xludf.DUMMYFUNCTION("GOOGLEFINANCE(A82,""Name"")"),"#N/A") -> #N/A | C82: 33.111.246/0001-90 | D82: Bens Industriais | E82: Construção e Engenharia | F82: Engenharia Consultiva | G82: Ação
A83: MILS3 | B83: =IFERROR(__xludf.DUMMYFUNCTION("GOOGLEFINANCE(A83,""Name"")"),"Mills Locacao Servicos E Logistica SA") -> Mills Locacao Servicos E Logistica SA | C83: 27.093.558/0001-15 | D83: Bens Industriais | E83: Construção e Engenharia | F83: Serviços Diversos | G83: Ação
A84: EMBR3 | B84: =IFERROR(__xludf.DUMMYFUNCTION("GOOGLEFINANCE(A84,""Name"")"),"#N/A") -> #N/A | C84: 07.689.002/0001-89 | D84: Bens Industriais | E84: Material de Transporte | F84: Material Aeronáutico e de Defesa | G84: Ação
A85: FRAS3 | B85: =IFERROR(__xludf.DUMMYFUNCTION("GOOGLEFINANCE(A85,""Name"")"),"Frasle Mobility SA") -> Frasle Mobility SA | C85: 88.610.126/0001-29 | D85: Bens Industriais | E85: Material de Transporte | F85: Material Rodoviário | G85: Ação
A86: POMO3 | B86: =IFERROR(__xludf.DUMMYFUNCTION("GOOGLEFINANCE(A86,""Name"")"),"Marcopolo SA") -> Marcopolo SA | C86: 88.611.835/0001-29 | D86: Bens Industriais | E86: Material de Transporte | F86: Material Rodoviário | G86: Ação
A87: POMO4 | B87: =IFERROR(__xludf.DUMMYFUNCTION("GOOGLEFINANCE(A87,""Name"")"),"Marcopolo SA Preference Shares") -> Marcopolo SA Preference Shares | C87: 88.611.835/0001-29 | D87: Bens Industriais | E87: Material de Transporte | F87: Material Rodoviário | G87: Ação
A88: RAPT3 | B88: =IFERROR(__xludf.DUMMYFUNCTION("GOOGLEFINANCE(A88,""Name"")"),"Randoncorp SA") -> Randoncorp SA | C88: 89.086.144/0001-16 | D88: Bens Industriais | E88: Material de Transporte | F88: Material Rodoviário | G88: Ação
A89: RAPT4 | B89: =IFERROR(__xludf.DUMMYFUNCTION("GOOGLEFINANCE(A89,""Name"")"),"Randoncorp SA Preference Shares") -> Randoncorp SA Preference Shares | C89: 89.086.144/0001-16 | D89: Bens Industriais | E89: Material de Transporte | F89: Material Rodoviário | G89: Ação
A90: RCSL3 | B90: =IFERROR(__xludf.DUMMYFUNCTION("GOOGLEFINANCE(A90,""Name"")"),"Recrusul SA") -> Recrusul SA | C90: 91.333.666/0001-17 | D90: Bens Industriais | E90: Material de Transporte | F90: Material Rodoviário | G90: Ação
A91: RCSL4 | B91: =IFERROR(__xludf.DUMMYFUNCTION("GOOGLEFINANCE(A91,""Name"")"),"Recrusul SA Preference Shares") -> Recrusul SA Preference Shares | C91: 91.333.666/0001-17 | D91: Bens Industriais | E91: Material de Transporte | F91: Material Rodoviário | G91: Ação
A92: RSUL3 | B92: =IFERROR(__xludf.DUMMYFUNCTION("GOOGLEFINANCE(A92,""Name"")"),"Metalurgica Riosulense SA") -> Metalurgica Riosulense SA | C92: 85.778.074/0001-06 | D92: Bens Industriais | E92: Material de Transporte | F92: Material Rodoviário | G92: Ação
A93: RSUL4 | B93: =IFERROR(__xludf.DUMMYFUNCTION("GOOGLEFINANCE(A93,""Name"")"),"Metalurgica Riosulense SA Preference Shares") -> Metalurgica Riosulense SA Preference Shares | C93: 85.778.074/0001-06 | D93: Bens Industriais | E93: Material de Transporte | F93: Material Rodoviário | G93: Ação
A94: TUPY3 | B94: =IFERROR(__xludf.DUMMYFUNCTION("GOOGLEFINANCE(A94,""Name"")"),"Tupy SA") -> Tupy SA | C94: 84.683.374/0001-49 | D94: Bens Industriais | E94: Material de Transporte | F94: Material Rodoviário | G94: Ação
A95: MWET3 | B95: =IFERROR(__xludf.DUMMYFUNCTION("GOOGLEFINANCE(A95,""Name"")"),"Wetzel SA") -> Wetzel SA | C95: 84.683.671/0001-94 | D95: Bens Industriais | E95: Material de Transporte | F95: Material Rodoviário | G95: Ação
A96: MWET4 | B96: =IFERROR(__xludf.DUMMYFUNCTION("GOOGLEFINANCE(A96,""Name"")"),"Wetzel SA Preference Shares") -> Wetzel SA Preference Shares | C96: 84.683.671/0001-94 | D96: Bens Industriais | E96: Material de Transporte | F96: Material Rodoviário | G96: Ação
A97: SHUL4 | B97: =IFERROR(__xludf.DUMMYFUNCTION("GOOGLEFINANCE(A97,""Name"")"),"Schulz SA Preference Shares") -> Schulz SA Preference Shares | C97: 84.693.183/0001-68 | D97: Bens Industriais | E97: Máquinas e Equipamentos | F97: Motores, Compressores e Outros | G97: Ação
A98: WEGE3 | B98: =IFERROR(__xludf.DUMMYFUNCTION("GOOGLEFINANCE(A98,""Name"")"),"Weg Cedear") -> Weg Cedear | C98: 84.429.695/0001-11 | D98: Bens Industriais | E98: Máquinas e Equipamentos | F98: Motores, Compressores e Outros | G98: Ação
A99: EALT3 | B99: =IFERROR(__xludf.DUMMYFUNCTION("GOOGLEFINANCE(A99,""Name"")"),"Electro Aco Altona SA") -> Electro Aco Altona SA | C99: 82.643.537/0001-34 | D99: Bens Industriais | E99: Máquinas e Equipamentos | F99: Máq. e Equip. Industriais | G99: Ação
A100: EALT4 | B100: =IFERROR(__xludf.DUMMYFUNCTION("GOOGLEFINANCE(A100,""Name"")"),"Electro Aco Altona SA Preference Shares") -> Electro Aco Altona SA Preference Shares | C100: 82.643.537/0001-34 | D100: Bens Industriais | E100: Máquinas e Equipamentos | F100: Máq. e Equip. Industriais | G100: Ação
...
